{
  "ticker": "002780",
  "name": "진흥기업",
  "quarterly": [
    {
      "period": "2012QQ3",
      "stac_yymm": "201209",
      "revenue": 3389,
      "operating_profit": 0,
      "net_income": -677,
      "op_margin": 0
    },
    {
      "period": "2012QQ4",
      "stac_yymm": "201212",
      "revenue": 4668,
      "operating_profit": 0,
      "net_income": -857,
      "op_margin": 0
    },
    {
      "period": "2013QQ1",
      "stac_yymm": "201303",
      "revenue": 732,
      "operating_profit": 0,
      "net_income": -83,
      "op_margin": 0
    },
    {
      "period": "2013QQ2",
      "stac_yymm": "201306",
      "revenue": 1989,
      "operating_profit": 0,
      "net_income": -96,
      "op_margin": 0
    },
    {
      "period": "2013QQ3",
      "stac_yymm": "201309",
      "revenue": 3136,
      "operating_profit": 0,
      "net_income": -166,
      "op_margin": 0,
      "yoy_revenue": -7.465329005606374
    },
    {
      "period": "2013QQ4",
      "stac_yymm": "201312",
      "revenue": 4796,
      "operating_profit": 0,
      "net_income": -724,
      "op_margin": 0,
      "yoy_revenue": 2.742073693230506
    },
    {
      "period": "2014QQ1",
      "stac_yymm": "201403",
      "revenue": 1143,
      "operating_profit": 0,
      "net_income": -38,
      "op_margin": 0,
      "yoy_revenue": 56.14754098360656
    },
    {
      "period": "2014QQ2",
      "stac_yymm": "201406",
      "revenue": 2807,
      "operating_profit": 0,
      "net_income": -78,
      "op_margin": 0,
      "yoy_revenue": 41.126194067370534
    },
    {
      "period": "2014QQ3",
      "stac_yymm": "201409",
      "revenue": 4277,
      "operating_profit": 0,
      "net_income": -82,
      "op_margin": 0,
      "yoy_revenue": 36.38392857142857
    },
    {
      "period": "2014QQ4",
      "stac_yymm": "201412",
      "revenue": 6381,
      "operating_profit": 0,
      "net_income": -176,
      "op_margin": 0,
      "yoy_revenue": 33.04837364470392
    },
    {
      "period": "2015QQ1",
      "stac_yymm": "201503",
      "revenue": 1383,
      "operating_profit": 0,
      "net_income": -7,
      "op_margin": 0,
      "yoy_revenue": 20.99737532808399
    },
    {
      "period": "2015QQ2",
      "stac_yymm": "201506",
      "revenue": 2956,
      "operating_profit": 0,
      "net_income": -531,
      "op_margin": 0,
      "yoy_revenue": 5.308158175988599
    },
    {
      "period": "2015QQ3",
      "stac_yymm": "201509",
      "revenue": 4675,
      "operating_profit": 0,
      "net_income": -472,
      "op_margin": 0,
      "yoy_revenue": 9.305588028992284
    },
    {
      "period": "2015QQ4",
      "stac_yymm": "201512",
      "revenue": 7278,
      "operating_profit": 0,
      "net_income": -428,
      "op_margin": 0,
      "yoy_revenue": 14.057357780912083
    },
    {
      "period": "2016QQ1",
      "stac_yymm": "201603",
      "revenue": 1408,
      "operating_profit": 0,
      "net_income": -29,
      "op_margin": 0,
      "yoy_revenue": 1.8076644974692697
    },
    {
      "period": "2016QQ2",
      "stac_yymm": "201606",
      "revenue": 3026,
      "operating_profit": 0,
      "net_income": -65,
      "op_margin": 0,
      "yoy_revenue": 2.3680649526387008
    },
    {
      "period": "2016QQ3",
      "stac_yymm": "201609",
      "revenue": 4632,
      "operating_profit": 0,
      "net_income": -59,
      "op_margin": 0,
      "yoy_revenue": -0.9197860962566844
    },
    {
      "period": "2016QQ4",
      "stac_yymm": "201612",
      "revenue": 6466,
      "operating_profit": 0,
      "net_income": -752,
      "op_margin": 0,
      "yoy_revenue": -11.156911239351471
    },
    {
      "period": "2017QQ1",
      "stac_yymm": "201703",
      "revenue": 1091,
      "operating_profit": 0,
      "net_income": 51,
      "op_margin": 0,
      "yoy_revenue": -22.514204545454543
    },
    {
      "period": "2017QQ2",
      "stac_yymm": "201706",
      "revenue": 2632,
      "operating_profit": 0,
      "net_income": 79,
      "op_margin": 0,
      "yoy_revenue": -13.02048909451421
    },
    {
      "period": "2017QQ3",
      "stac_yymm": "201709",
      "revenue": 4115,
      "operating_profit": 0,
      "net_income": 173,
      "op_margin": 0,
      "yoy_revenue": -11.161485319516409
    },
    {
      "period": "2017QQ4",
      "stac_yymm": "201712",
      "revenue": 5733,
      "operating_profit": 0,
      "net_income": 218,
      "op_margin": 0,
      "yoy_revenue": -11.336220228889577
    },
    {
      "period": "2018QQ1",
      "stac_yymm": "201803",
      "revenue": 1483,
      "operating_profit": 0,
      "net_income": 114,
      "op_margin": 0,
      "yoy_revenue": 35.93033913840513
    },
    {
      "period": "2018QQ4",
      "stac_yymm": "201812",
      "revenue": 6712,
      "operating_profit": 0,
      "net_income": 61,
      "op_margin": 0,
      "yoy_revenue": 17.07657421943136
    },
    {
      "period": "2019QQ4",
      "stac_yymm": "201912",
      "revenue": 5465,
      "operating_profit": 0,
      "net_income": 203,
      "op_margin": 0,
      "yoy_revenue": -18.578665077473183
    },
    {
      "period": "2020QQ4",
      "stac_yymm": "202012",
      "revenue": 3772,
      "operating_profit": 0,
      "net_income": 204,
      "op_margin": 0,
      "yoy_revenue": -30.97895699908509
    },
    {
      "period": "2021QQ4",
      "stac_yymm": "202112",
      "revenue": 4442,
      "operating_profit": 0,
      "net_income": 534,
      "op_margin": 0,
      "yoy_revenue": 17.762460233297986
    },
    {
      "period": "2022QQ4",
      "stac_yymm": "202212",
      "revenue": 6289,
      "operating_profit": 0,
      "net_income": 496,
      "op_margin": 0,
      "yoy_revenue": 41.580369203061686
    },
    {
      "period": "2023QQ4",
      "stac_yymm": "202312",
      "revenue": 7594,
      "operating_profit": 0,
      "net_income": 453,
      "op_margin": 0,
      "yoy_revenue": 20.75051677532199
    },
    {
      "period": "2024QQ4",
      "stac_yymm": "202412",
      "revenue": 7262,
      "operating_profit": 0,
      "net_income": 22,
      "op_margin": 0,
      "yoy_revenue": -4.371872530945483
    }
  ],
  "annual": [
    {
      "year": "2024",
      "revenue": 7262,
      "operating_profit": 0,
      "net_income": 22,
      "op_margin": 0,
      "net_margin": 0.3029468465987331
    },
    {
      "year": "2023",
      "revenue": 7594,
      "operating_profit": 0,
      "net_income": 453,
      "op_margin": 0,
      "net_margin": 5.96523571240453
    },
    {
      "year": "2022",
      "revenue": 6289,
      "operating_profit": 0,
      "net_income": 496,
      "op_margin": 0,
      "net_margin": 7.886786452536174
    },
    {
      "year": "2021",
      "revenue": 4442,
      "operating_profit": 0,
      "net_income": 534,
      "op_margin": 0,
      "net_margin": 12.021611886537595
    },
    {
      "year": "2020",
      "revenue": 3772,
      "operating_profit": 0,
      "net_income": 204,
      "op_margin": 0,
      "net_margin": 5.408271474019088
    },
    {
      "year": "2019",
      "revenue": 5465,
      "operating_profit": 0,
      "net_income": 203,
      "op_margin": 0,
      "net_margin": 3.714547118023788
    },
    {
      "year": "2018",
      "revenue": 6712,
      "operating_profit": 0,
      "net_income": 61,
      "op_margin": 0,
      "net_margin": 0.9088200238379023
    },
    {
      "year": "2017",
      "revenue": 5733,
      "operating_profit": 0,
      "net_income": 218,
      "op_margin": 0,
      "net_margin": 3.8025466596895168
    },
    {
      "year": "2016",
      "revenue": 6466,
      "operating_profit": 0,
      "net_income": -752,
      "op_margin": 0,
      "net_margin": -11.630064955150015
    },
    {
      "year": "2015",
      "revenue": 7278,
      "operating_profit": 0,
      "net_income": -428,
      "op_margin": 0,
      "net_margin": -5.880736466062105
    },
    {
      "year": "2014",
      "revenue": 6381,
      "operating_profit": 0,
      "net_income": -176,
      "op_margin": 0,
      "net_margin": -2.758188371728569
    },
    {
      "year": "2013",
      "revenue": 4796,
      "operating_profit": 0,
      "net_income": -724,
      "op_margin": 0,
      "net_margin": -15.095913261050875
    },
    {
      "year": "2012",
      "revenue": 4668,
      "operating_profit": 0,
      "net_income": -857,
      "op_margin": 0,
      "net_margin": -18.35904027420737
    },
    {
      "year": "2011",
      "revenue": 5564,
      "operating_profit": 0,
      "net_income": -2138,
      "op_margin": 0,
      "net_margin": -38.425593098490296
    },
    {
      "year": "2010",
      "revenue": 6005,
      "operating_profit": 0,
      "net_income": -1982,
      "op_margin": 0,
      "net_margin": -33.00582847626978
    },
    {
      "year": "2009",
      "revenue": 6217,
      "operating_profit": 0,
      "net_income": -1495,
      "op_margin": 0,
      "net_margin": -24.046967990992442
    },
    {
      "year": "2008",
      "revenue": 6044,
      "operating_profit": 0,
      "net_income": 6,
      "op_margin": 0,
      "net_margin": 0.09927200529450694
    },
    {
      "year": "2007",
      "revenue": 5947,
      "operating_profit": 0,
      "net_income": 62,
      "op_margin": 0,
      "net_margin": 1.0425424583823777
    },
    {
      "year": "2006",
      "revenue": 4952,
      "operating_profit": 0,
      "net_income": 66,
      "op_margin": 0,
      "net_margin": 1.3327948303715669
    },
    {
      "year": "2005",
      "revenue": 3495,
      "operating_profit": 0,
      "net_income": 193,
      "op_margin": 0,
      "net_margin": 5.5221745350500715
    },
    {
      "year": "2004",
      "revenue": 3302,
      "operating_profit": 0,
      "net_income": 86,
      "op_margin": 0,
      "net_margin": 2.604482132041187
    }
  ],
  "ratios": {
    "per": 0,
    "pbr": 0,
    "roe": 0.81,
    "eps": 15,
    "bps": 1830,
    "debt_ratio": 102.63
  }
}
