{"meta":{"schema":1,"total":22470,"page":12,"pages":23},"data":[{"g":"구리시","n":"엘에이치이스트힐","a":60,"p":59000,"d":"2026-01-05","f":9},{"g":"남양주시","n":"호평파라곤","a":131,"p":59000,"d":"2026-01-31","f":6},{"g":"남양주시","n":"호평마을대주파크빌","a":145,"p":59000,"d":"2026-01-13","f":12},{"g":"남양주시","n":"더힐포레4단지","a":76,"p":59000,"d":"2026-01-05","f":8},{"g":"오산시","n":"호반써밋라포레","a":85,"p":59000,"d":"2026-01-16","f":9},{"g":"시흥시","n":"장현호반써밋","a":85,"p":59000,"d":"2026-01-28","f":12},{"g":"시흥시","n":"제일풍경채더숲","a":85,"p":59000,"d":"2026-01-23","f":7},{"g":"시흥시","n":"은계어반리더스","a":85,"p":59000,"d":"2026-01-19","f":26},{"g":"시흥시","n":"호반베르디움센트로하임","a":85,"p":59000,"d":"2026-01-17","f":21},{"g":"시흥시","n":"네이처하임","a":74,"p":59000,"d":"2026-01-08","f":16},{"g":"군포시","n":"우륵","a":85,"p":59000,"d":"2026-01-16","f":4},{"g":"의왕시","n":"의왕역푸르지오라포레","a":75,"p":59000,"d":"2026-01-21","f":5},{"g":"의왕시","n":"인스빌1단지","a":102,"p":59000,"d":"2026-01-23","f":7},{"g":"하남시","n":"라인","a":85,"p":59000,"d":"2026-01-28","f":5},{"g":"용인시 처인구","n":"힐스테이트몬테로이2단지","a":85,"p":59000,"d":"2026-01-29","f":4},{"g":"용인시 처인구","n":"힐스테이트용인둔전역","a":76,"p":59000,"d":"2026-01-28","f":20},{"g":"용인시 처인구","n":"용인명지대역동원로얄듀크","a":85,"p":59000,"d":"2026-01-17","f":1},{"g":"용인시 기흥구","n":"하마비마을동일하이빌2","a":110,"p":59000,"d":"2026-01-12","f":5},{"g":"용인시 기흥구","n":"신흥덕롯데캐슬레이시티","a":60,"p":59000,"d":"2026-01-17","f":7},{"g":"용인시 기흥구","n":"영통로효성해링턴플레이스1차","a":60,"p":59000,"d":"2026-01-28","f":2},{"g":"용인시 기흥구","n":"구성역효성해링턴플레이스","a":62,"p":59000,"d":"2026-01-23","f":12},{"g":"용인시 기흥구","n":"한성1","a":47,"p":59000,"d":"2026-01-22","f":4},{"g":"용인시 기흥구","n":"스파팰리스리가","a":85,"p":59000,"d":"2026-01-11","f":1},{"g":"용인시 기흥구","n":"백현마을코아루","a":122,"p":59000,"d":"2026-01-02","f":2},{"g":"용인시 기흥구","n":"신흥덕롯데캐슬레이시티","a":60,"p":59000,"d":"2026-01-07","f":27},{"g":"용인시 기흥구","n":"신동백롯데캐슬에코2단지","a":85,"p":59000,"d":"2026-01-08","f":10},{"g":"용인시 수지구","n":"용인 죽전 효성해링턴 플레이스","a":60,"p":59000,"d":"2026-01-28","f":11},{"g":"용인시 수지구","n":"도담마을죽전파크빌","a":60,"p":59000,"d":"2026-01-19","f":17},{"g":"용인시 수지구","n":"죽전현대1차","a":85,"p":59000,"d":"2026-01-03","f":16},{"g":"용인시 수지구","n":"도담마을죽전파크빌","a":85,"p":59000,"d":"2026-01-09","f":14},{"g":"용인시 수지구","n":"삼익아파트","a":60,"p":59000,"d":"2026-01-03","f":9},{"g":"파주시","n":"초롱꽃마을6단지금강펜테리움","a":85,"p":59000,"d":"2026-01-08","f":13},{"g":"김포시","n":"e편한세상캐널시티","a":85,"p":59000,"d":"2026-01-28","f":14},{"g":"김포시","n":"한강신도시e편한세상","a":102,"p":59000,"d":"2026-01-24","f":12},{"g":"김포시","n":"힐스테이트 리버시티 2단지","a":85,"p":59000,"d":"2026-01-31","f":14},{"g":"김포시","n":"캐슬앤파밀리에시티 2단지","a":85,"p":59000,"d":"2026-01-26","f":15},{"g":"김포시","n":"e편한세상캐널시티","a":84,"p":59000,"d":"2026-01-28","f":21},{"g":"김포시","n":"풍무센트럴푸르지오","a":60,"p":59000,"d":"2026-01-29","f":11},{"g":"김포시","n":"e편한세상캐널시티","a":85,"p":59000,"d":"2026-01-24","f":18},{"g":"김포시","n":"캐슬앤파밀리에시티 1단지","a":85,"p":59000,"d":"2026-01-17","f":2},{"g":"김포시","n":"캐슬앤파밀리에시티 1단지","a":85,"p":59000,"d":"2026-01-02","f":14},{"g":"김포시","n":"수기마을힐스테이트1단지","a":85,"p":59000,"d":"2026-01-03","f":8},{"g":"화성시 동탄구","n":"푸르지오","a":60,"p":59000,"d":"2026-01-21","f":11},{"g":"화성시 동탄구","n":"동탄숲속마을자연앤경남아너스빌(1115-0)","a":77,"p":59000,"d":"2026-01-15","f":23},{"g":"화성시 동탄구","n":"동탄금강펜테리움센트럴파크Ⅳ","a":85,"p":59000,"d":"2026-01-10","f":9},{"g":"화성시 동탄구","n":"동탄숲속마을자연앤경남아너스빌(1115-0)","a":85,"p":59000,"d":"2026-01-08","f":15},{"g":"광주시","n":"이편한세상광주역4단지","a":60,"p":59000,"d":"2026-01-26","f":14},{"g":"광주시","n":"경기광주역금호리첸시아","a":75,"p":59000,"d":"2026-01-21","f":5},{"g":"광주시","n":"힐스테이트삼동역","a":64,"p":59000,"d":"2026-01-05","f":1},{"g":"광주시","n":"광주태전아이파크","a":85,"p":59000,"d":"2026-01-04","f":16},{"g":"양주시","n":"양주옥정신도시디에트르프레스티지","a":108,"p":59000,"d":"2026-01-20","f":11},{"g":"양평군","n":"센트럴파크써밋","a":80,"p":59000,"d":"2026-01-24","f":23},{"g":"미추홀구","n":"인천 SK Sky VIEW","a":85,"p":58900,"d":"2026-01-03","f":12},{"g":"시흥시","n":"장현호반써밋","a":85,"p":58900,"d":"2026-01-18","f":25},{"g":"하남시","n":"부영","a":50,"p":58900,"d":"2026-01-05","f":12},{"g":"용인시 기흥구","n":"신흥덕롯데캐슬레이시티","a":60,"p":58900,"d":"2026-01-24","f":5},{"g":"용인시 기흥구","n":"하마비마을동부센트레빌","a":126,"p":58900,"d":"2026-01-17","f":8},{"g":"용인시 기흥구","n":"신흥덕롯데캐슬레이시티","a":60,"p":58900,"d":"2026-01-09","f":17},{"g":"김포시","n":"풍무센트럴푸르지오","a":60,"p":58900,"d":"2026-01-23","f":7},{"g":"중랑구","n":"엘지,쌍용아파트","a":68,"p":58800,"d":"2026-01-12","f":2},{"g":"강북구","n":"형인휴아름","a":83,"p":58800,"d":"2026-01-20","f":6},{"g":"도봉구","n":"한신","a":85,"p":58800,"d":"2026-01-17","f":10},{"g":"도봉구","n":"초안산신도브래뉴","a":78,"p":58800,"d":"2026-01-02","f":9},{"g":"노원구","n":"동아불암","a":85,"p":58800,"d":"2026-01-17","f":1},{"g":"노원구","n":"초안산쌍용스윗닷홈","a":85,"p":58800,"d":"2026-01-22","f":1},{"g":"노원구","n":"상계1차중앙하이츠","a":60,"p":58800,"d":"2026-01-17","f":15},{"g":"은평구","n":"거장메카","a":51,"p":58800,"d":"2026-01-18","f":10},{"g":"양천구","n":"양천벽산블루밍1단지","a":60,"p":58800,"d":"2026-01-21","f":13},{"g":"양천구","n":"코아루2단지","a":85,"p":58800,"d":"2026-01-06","f":5},{"g":"관악구","n":"은천2단지아파트","a":50,"p":58800,"d":"2026-01-10","f":7},{"g":"관악구","n":"LIG대학마을(건영아파트3차)","a":69,"p":58800,"d":"2026-01-05","f":3},{"g":"부평구","n":"부평두산위브더파크","a":75,"p":58800,"d":"2026-01-17","f":13},{"g":"수원시 권선구","n":"수원아이파크시티7단지","a":60,"p":58800,"d":"2026-01-16","f":14},{"g":"수원시 권선구","n":"수원하늘채더퍼스트2단지","a":60,"p":58800,"d":"2026-01-29","f":11},{"g":"수원시 권선구","n":"수원시청역SKVIEW","a":83,"p":58800,"d":"2026-01-05","f":8},{"g":"평택시","n":"호반써밋고덕국제신도시에듀파크","a":84,"p":58800,"d":"2026-01-03","f":23},{"g":"안산시 단원구","n":"초지역메이저타운푸르지오파크단지","a":60,"p":58800,"d":"2026-01-12","f":21},{"g":"고양시 일산서구","n":"후곡마을(한양)","a":85,"p":58800,"d":"2026-01-06","f":13},{"g":"구리시","n":"아름마을일신","a":60,"p":58800,"d":"2026-01-28","f":4},{"g":"구리시","n":"건영","a":84,"p":58800,"d":"2026-01-09","f":11},{"g":"구리시","n":"엘에이치이스트힐","a":60,"p":58800,"d":"2026-01-10","f":7},{"g":"남양주시","n":"쌍용스윗닷홈리버","a":85,"p":58800,"d":"2026-01-28","f":18},{"g":"남양주시","n":"경남아너스빌","a":85,"p":58800,"d":"2026-01-20","f":6},{"g":"시흥시","n":"은계어반리더스","a":85,"p":58800,"d":"2026-01-04","f":24},{"g":"의왕시","n":"의왕역푸르지오라포레","a":75,"p":58800,"d":"2026-01-27","f":15},{"g":"용인시 기흥구","n":"신흥덕롯데캐슬레이시티","a":60,"p":58800,"d":"2026-01-24","f":8},{"g":"화성시 동탄구","n":"동탄파크푸르지오","a":85,"p":58800,"d":"2026-01-31","f":8},{"g":"부천시 소사구","n":"일루미스테이트","a":60,"p":58750,"d":"2026-01-28","f":27},{"g":"노원구","n":"주공2","a":60,"p":58700,"d":"2026-01-31","f":11},{"g":"구로구","n":"한진","a":60,"p":58700,"d":"2026-01-12","f":22},{"g":"관악구","n":"예촌BC","a":90,"p":58700,"d":"2026-01-15","f":1},{"g":"연수구","n":"롯데캐슬캠퍼스타운","a":60,"p":58700,"d":"2026-01-22","f":15},{"g":"부평구","n":"힐스테이트부평","a":60,"p":58700,"d":"2026-01-24","f":14},{"g":"부평구","n":"상우신명보람","a":111,"p":58700,"d":"2026-01-23","f":3},{"g":"부평구","n":"부평캐슬&더샵퍼스트","a":60,"p":58700,"d":"2026-01-07","f":27},{"g":"서구","n":"루원시티 대성베르힐","a":85,"p":58700,"d":"2026-01-24","f":19},{"g":"서구","n":"검단신도시모아엘가그랑데","a":60,"p":58700,"d":"2026-01-24","f":8},{"g":"서구","n":"루원제일풍경채","a":84,"p":58700,"d":"2026-01-06","f":24},{"g":"수원시 팔달구","n":"화서역블루밍푸른숲","a":85,"p":58700,"d":"2026-01-10","f":6},{"g":"의정부시","n":"e편한세상신곡포레스타뷰","a":85,"p":58700,"d":"2026-01-21","f":17},{"g":"의정부시","n":"e편한세상신곡파크프라임","a":85,"p":58700,"d":"2026-01-17","f":9},{"g":"부천시 소사구","n":"소새울KCC스위첸","a":85,"p":58700,"d":"2026-01-14","f":5},{"g":"구리시","n":"주공1","a":60,"p":58700,"d":"2026-01-02","f":15},{"g":"시흥시","n":"시흥능곡역장현리슈빌퍼스트클래스","a":112,"p":58700,"d":"2026-01-23","f":17},{"g":"용인시 수지구","n":"내대지마을죽전이편한세상","a":85,"p":58700,"d":"2026-01-09","f":9},{"g":"파주시","n":"한울마을1단지운정신도시IPARK","a":60,"p":58700,"d":"2026-01-26","f":14},{"g":"김포시","n":"풍무푸르지오센트레빌","a":73,"p":58700,"d":"2026-01-07","f":2},{"g":"화성시 동탄구","n":"동탄역 신미주","a":85,"p":58700,"d":"2026-01-24","f":7},{"g":"화성시 동탄구","n":"동탄숲속마을자연앤경남아너스빌(1115-0)","a":85,"p":58700,"d":"2026-01-20","f":6},{"g":"화성시 동탄구","n":"동탄금강펜테리움센트럴파크Ⅳ","a":85,"p":58700,"d":"2026-01-10","f":8},{"g":"광주시","n":"신현라온프라이빗","a":84,"p":58700,"d":"2026-01-06","f":10},{"g":"구로구","n":"구로두산","a":52,"p":58600,"d":"2026-01-26","f":9},{"g":"의정부시","n":"장암더샵포레스트","a":85,"p":58600,"d":"2026-01-22","f":10},{"g":"구리시","n":"아름마을삼성","a":60,"p":58600,"d":"2026-01-15","f":7},{"g":"화성시 동탄구","n":"동탄역 신미주","a":85,"p":58600,"d":"2026-01-10","f":6},{"g":"부천시 소사구","n":"일루미스테이트","a":60,"p":58550,"d":"2026-01-25","f":7},{"g":"동대문구","n":"휘경미소지움","a":60,"p":58500,"d":"2026-01-31","f":1},{"g":"동대문구","n":"르메이에르7차(313-8)","a":85,"p":58500,"d":"2026-01-16","f":4},{"g":"중랑구","n":"경남아너스빌","a":63,"p":58500,"d":"2026-01-28","f":1},{"g":"중랑구","n":"금호어울림(580)","a":60,"p":58500,"d":"2026-01-17","f":6},{"g":"성북구","n":"길음뉴타운경남아너스빌","a":50,"p":58500,"d":"2026-01-10","f":2},{"g":"강북구","n":"형인휴아름","a":84,"p":58500,"d":"2026-01-31","f":4},{"g":"강북구","n":"벽산라이브파크","a":60,"p":58500,"d":"2026-01-10","f":7},{"g":"도봉구","n":"한신","a":85,"p":58500,"d":"2026-01-29","f":1},{"g":"도봉구","n":"한신","a":85,"p":58500,"d":"2026-01-10","f":5},{"g":"노원구","n":"상계2차중앙하이츠","a":60,"p":58500,"d":"2026-01-14","f":3},{"g":"노원구","n":"건영","a":53,"p":58500,"d":"2026-01-09","f":6},{"g":"양천구","n":"대성유니드1차","a":60,"p":58500,"d":"2026-01-20","f":5},{"g":"강서구","n":"가양도시개발9-2단지","a":34,"p":58500,"d":"2026-01-23","f":11},{"g":"구로구","n":"청구","a":60,"p":58500,"d":"2026-01-17","f":19},{"g":"미추홀구","n":"주안파크자이더플래티넘","a":85,"p":58500,"d":"2026-01-18","f":10},{"g":"연수구","n":"더샵그린스퀘어","a":65,"p":58500,"d":"2026-01-19","f":11},{"g":"연수구","n":"송도풍림아이원2단지","a":85,"p":58500,"d":"2026-01-09","f":13},{"g":"남동구","n":"에코메트로5","a":85,"p":58500,"d":"2026-01-06","f":26},{"g":"서구","n":"호반써밋프라임뷰","a":84,"p":58500,"d":"2026-01-29","f":22},{"g":"서구","n":"호반베르디움","a":85,"p":58500,"d":"2026-01-24","f":14},{"g":"서구","n":"검단신도시모아엘가그랑데","a":60,"p":58500,"d":"2026-01-19","f":22},{"g":"서구","n":"검단신도시모아엘가그랑데","a":60,"p":58500,"d":"2026-01-16","f":20},{"g":"수원시 장안구","n":"화서역 위너스 파크","a":85,"p":58500,"d":"2026-01-21","f":8},{"g":"수원시 권선구","n":"호매실역서희스타힐스","a":85,"p":58500,"d":"2026-01-31","f":8},{"g":"수원시 권선구","n":"쌍용더플래티넘오목천역","a":60,"p":58500,"d":"2026-01-16","f":12},{"g":"수원시 권선구","n":"수원하늘채더퍼스트2단지","a":60,"p":58500,"d":"2026-01-09","f":14},{"g":"수원시 영통구","n":"엘지동수원자이","a":85,"p":58500,"d":"2026-01-26","f":9},{"g":"수원시 영통구","n":"영통자이","a":60,"p":58500,"d":"2026-01-16","f":7},{"g":"수원시 영통구","n":"동수원자이1차","a":85,"p":58500,"d":"2026-01-13","f":8},{"g":"의정부시","n":"의정부롯데캐슬골드파크2단지","a":85,"p":58500,"d":"2026-01-28","f":17},{"g":"안양시 만안구","n":"성원상떼빌","a":109,"p":58500,"d":"2026-01-21","f":1},{"g":"안양시 만안구","n":"성원1","a":85,"p":58500,"d":"2026-01-16","f":17},{"g":"안양시 동안구","n":"안양임곡휴먼시아","a":60,"p":58500,"d":"2026-01-16","f":10},{"g":"부천시 원미구","n":"부천중동해링턴플레이스","a":60,"p":58500,"d":"2026-01-07","f":16},{"g":"부천시 소사구","n":"일루미스테이트","a":60,"p":58500,"d":"2026-01-23","f":10},{"g":"부천시 소사구","n":"부천범박힐스테이트4단지","a":84,"p":58500,"d":"2026-01-24","f":3},{"g":"부천시 소사구","n":"일루미스테이트","a":60,"p":58500,"d":"2026-01-17","f":23},{"g":"광명시","n":"동양메이저2차","a":60,"p":58500,"d":"2026-01-03","f":18},{"g":"평택시","n":"힐스테이트지제역퍼스티움","a":85,"p":58500,"d":"2026-01-31","f":20},{"g":"안산시 단원구","n":"안산라프리모","a":85,"p":58500,"d":"2026-01-24","f":27},{"g":"고양시 덕양구","n":"별빛마을(건영)10","a":77,"p":58500,"d":"2026-01-17","f":5},{"g":"고양시 일산동구","n":"강촌마을(동아)","a":85,"p":58500,"d":"2026-01-24","f":7},{"g":"고양시 일산동구","n":"위시티블루밍3단지","a":102,"p":58500,"d":"2026-01-18","f":18},{"g":"고양시 일산서구","n":"킨텍스아이파크","a":120,"p":58500,"d":"2026-01-27","f":14},{"g":"구리시","n":"원일아름","a":85,"p":58500,"d":"2026-01-24","f":22},{"g":"구리시","n":"원일아름","a":85,"p":58500,"d":"2026-01-16","f":21},{"g":"구리시","n":"주공6","a":58,"p":58500,"d":"2026-01-09","f":3},{"g":"오산시","n":"호반써밋라포레","a":85,"p":58500,"d":"2026-01-10","f":11},{"g":"시흥시","n":"호반베르디움센트로하임","a":85,"p":58500,"d":"2026-01-28","f":5},{"g":"시흥시","n":"호반베르디움더프라임","a":84,"p":58500,"d":"2026-01-19","f":15},{"g":"군포시","n":"용호마을e-편한세상","a":85,"p":58500,"d":"2026-01-30","f":8},{"g":"의왕시","n":"의왕푸르지오포레움2블럭","a":60,"p":58500,"d":"2026-01-23","f":3},{"g":"용인시 기흥구","n":"초원마을성원상떼빌2차","a":85,"p":58500,"d":"2026-01-24","f":17},{"g":"용인시 기흥구","n":"신동백롯데캐슬에코1단지","a":85,"p":58500,"d":"2026-01-12","f":16},{"g":"파주시","n":"초롱꽃마을12단지e편한세상운정어반프라임","a":85,"p":58500,"d":"2026-01-22","f":6},{"g":"화성시 동탄구","n":"동탄역이지더원","a":60,"p":58500,"d":"2026-01-07","f":8},{"g":"화성시 동탄구","n":"레이크힐 반도유보라 아이비파크 10.2","a":97,"p":58500,"d":"2026-01-21","f":12},{"g":"화성시 동탄구","n":"동탄역포레너스","a":85,"p":58500,"d":"2026-01-03","f":1},{"g":"광주시","n":"이편한세상광주역4단지","a":60,"p":58500,"d":"2026-01-16","f":13},{"g":"광주시","n":"광주태전아이파크","a":85,"p":58500,"d":"2026-01-09","f":20},{"g":"미추홀구","n":"인천 SK Sky VIEW","a":85,"p":58400,"d":"2026-01-14","f":30},{"g":"수원시 영통구","n":"영통자이","a":60,"p":58400,"d":"2026-01-14","f":11},{"g":"의정부시","n":"의정부롯데캐슬골드파크1단지","a":85,"p":58400,"d":"2026-01-07","f":27},{"g":"안산시 단원구","n":"안산라프리모","a":85,"p":58400,"d":"2026-01-31","f":11},{"g":"시흥시","n":"은계어반리더스","a":85,"p":58400,"d":"2026-01-31","f":12},{"g":"시흥시","n":"은계어반리더스","a":85,"p":58400,"d":"2026-01-12","f":8},{"g":"시흥시","n":"시흥능곡역장현리슈빌퍼스트클래스","a":112,"p":58400,"d":"2026-01-17","f":14},{"g":"화성시 동탄구","n":"동탄파크푸르지오","a":85,"p":58400,"d":"2026-01-09","f":6},{"g":"노원구","n":"염광","a":59,"p":58300,"d":"2026-01-14","f":15},{"g":"수원시 권선구","n":"호매실역서희스타힐스","a":85,"p":58300,"d":"2026-01-13","f":9},{"g":"수원시 영통구","n":"현대힐스테이트","a":60,"p":58300,"d":"2026-01-28","f":15},{"g":"부천시 원미구","n":"백송마을(풍림아이원)","a":60,"p":58300,"d":"2026-01-18","f":9},{"g":"고양시 덕양구","n":"별빛마을9단지(901동에서906동)","a":85,"p":58300,"d":"2026-01-09","f":4},{"g":"군포시","n":"우방,한국공영목련","a":85,"p":58300,"d":"2026-01-28","f":6},{"g":"의왕시","n":"대명구름채","a":85,"p":58300,"d":"2026-01-30","f":20},{"g":"용인시 처인구","n":"힐스테이트용인둔전역","a":76,"p":58300,"d":"2026-01-26","f":22},{"g":"파주시","n":"한빛마을9단지롯데캐슬1차","a":84,"p":58300,"d":"2026-01-07","f":14},{"g":"화성시 병점구","n":"서동탄역파크자이2차","a":85,"p":58300,"d":"2026-01-30","f":17},{"g":"양주시","n":"덕계역대광로제비앙더메트로팰리스","a":101,"p":58300,"d":"2026-01-12","f":27},{"g":"안양시 만안구","n":"안양명학역유보라더스마트","a":60,"p":58250,"d":"2026-01-26","f":23},{"g":"평택시","n":"고덕국제신도시파라곤에듀포레","a":85,"p":58250,"d":"2026-01-30","f":11},{"g":"동대문구","n":"동서울한양","a":60,"p":58200,"d":"2026-01-24","f":7},{"g":"은평구","n":"거장메카","a":49,"p":58200,"d":"2026-01-25","f":11},{"g":"강서구","n":"방화5","a":50,"p":58200,"d":"2026-01-26","f":1},{"g":"수원시 영통구","n":"벽적골9단지주공","a":59,"p":58200,"d":"2026-01-13","f":13},{"g":"부천시 원미구","n":"백송마을(풍림아이원)","a":60,"p":58200,"d":"2026-01-14","f":9},{"g":"용인시 기흥구","n":"성산마을신영지웰","a":102,"p":58200,"d":"2026-01-27","f":7},{"g":"화성시 동탄구","n":"동탄역이지더원","a":60,"p":58200,"d":"2026-01-31","f":2},{"g":"화성시 동탄구","n":"동탄2신도시 베라체","a":85,"p":58200,"d":"2026-01-23","f":3},{"g":"서초구","n":"대림서초리시온","a":50,"p":58100,"d":"2026-01-17","f":7},{"g":"서구","n":"루원호반베르디움더센트럴","a":73,"p":58100,"d":"2026-01-20","f":23},{"g":"중랑구","n":"신내6대주","a":50,"p":58000,"d":"2026-01-31","f":6},{"g":"중랑구","n":"신안1","a":60,"p":58000,"d":"2026-01-21","f":7},{"g":"중랑구","n":"용마한신","a":59,"p":58000,"d":"2026-01-16","f":8},{"g":"성북구","n":"우방아파트","a":60,"p":58000,"d":"2026-01-21","f":11},{"g":"도봉구","n":"대우","a":60,"p":58000,"d":"2026-01-09","f":10},{"g":"노원구","n":"상계주공1(고층)","a":58,"p":58000,"d":"2026-01-29","f":2},{"g":"노원구","n":"상계주공4(고층)","a":58,"p":58000,"d":"2026-01-31","f":2},{"g":"노원구","n":"상계2차중앙하이츠","a":60,"p":58000,"d":"2026-01-31","f":8},{"g":"노원구","n":"극동","a":56,"p":58000,"d":"2026-01-30","f":9},{"g":"노원구","n":"보람아파트","a":69,"p":58000,"d":"2026-01-28","f":15},{"g":"노원구","n":"상계주공10(저층)","a":55,"p":58000,"d":"2026-01-22","f":3},{"g":"노원구","n":"태강아파트(아이파크)","a":50,"p":58000,"d":"2026-01-22","f":4},{"g":"노원구","n":"보람아파트","a":69,"p":58000,"d":"2026-01-22","f":2},{"g":"노원구","n":"중계무지개","a":50,"p":58000,"d":"2026-01-16","f":13},{"g":"노원구","n":"중계그린1단지","a":50,"p":58000,"d":"2026-01-13","f":3},{"g":"양천구","n":"성원2","a":60,"p":58000,"d":"2026-01-08","f":1},{"g":"강서구","n":"삼성꽃마을","a":60,"p":58000,"d":"2026-01-16","f":10},{"g":"강서구","n":"가양도시개발9-2단지","a":34,"p":58000,"d":"2026-01-26","f":6},{"g":"구로구","n":"구로지웰","a":60,"p":58000,"d":"2026-01-28","f":4},{"g":"금천구","n":"관악산벽산타운5","a":85,"p":58000,"d":"2026-01-21","f":15},{"g":"금천구","n":"SM엘루이","a":71,"p":58000,"d":"2026-01-17","f":8},{"g":"영등포구","n":"미주프라자","a":60,"p":58000,"d":"2026-01-13","f":12},{"g":"영등포구","n":"당산대우","a":46,"p":58000,"d":"2026-01-10","f":16},{"g":"관악구","n":"은천2단지아파트","a":50,"p":58000,"d":"2026-01-22","f":4},{"g":"서초구","n":"더샵서초","a":30,"p":58000,"d":"2026-01-12","f":30},{"g":"강동구","n":"한신아파트","a":58,"p":58000,"d":"2026-01-08","f":4},{"g":"강동구","n":"암사라인","a":59,"p":58000,"d":"2026-01-10","f":5},{"g":"미추홀구","n":"인천 SK Sky VIEW","a":85,"p":58000,"d":"2026-01-20","f":14},{"g":"미추홀구","n":"인천 SK Sky VIEW","a":85,"p":58000,"d":"2026-01-23","f":33},{"g":"연수구","n":"송도풍림아이원4단지","a":85,"p":58000,"d":"2026-01-28","f":10},{"g":"연수구","n":"송도오션파크베르디움","a":76,"p":58000,"d":"2026-01-14","f":4},{"g":"남동구","n":"에코메트로9","a":124,"p":58000,"d":"2026-01-12","f":16},{"g":"부평구","n":"힐스테이트부평","a":60,"p":58000,"d":"2026-01-16","f":13},{"g":"부평구","n":"부평캐슬&더샵퍼스트","a":60,"p":58000,"d":"2026-01-10","f":14},{"g":"부평구","n":"더샵부평센트럴시티","a":69,"p":58000,"d":"2026-01-01","f":26},{"g":"서구","n":"호반써밋프라임뷰","a":84,"p":58000,"d":"2026-01-23","f":6},{"g":"서구","n":"청라반도유보라","a":102,"p":58000,"d":"2026-01-27","f":9},{"g":"서구","n":"청라우미린","a":85,"p":58000,"d":"2026-01-08","f":16},{"g":"수원시 장안구","n":"꽃뫼마을신안","a":85,"p":58000,"d":"2026-01-28","f":13},{"g":"수원시 권선구","n":"수원아이파크시티6단지","a":75,"p":58000,"d":"2026-01-28","f":3},{"g":"수원시 권선구","n":"호매실엔루체(N'LUCE)","a":85,"p":58000,"d":"2026-01-09","f":23},{"g":"수원시 권선구","n":"대림","a":97,"p":58000,"d":"2026-01-16","f":9},{"g":"수원시 권선구","n":"호매실더센트라고","a":85,"p":58000,"d":"2026-01-31","f":15},{"g":"수원시 권선구","n":"쌍용더플래티넘오목천역","a":60,"p":58000,"d":"2026-01-29","f":13},{"g":"수원시 권선구","n":"수원아이파크시티3단지","a":85,"p":58000,"d":"2026-01-27","f":9},{"g":"수원시 권선구","n":"일월청구","a":135,"p":58000,"d":"2026-01-23","f":1},{"g":"수원시 권선구","n":"수원아이파크시티7단지","a":60,"p":58000,"d":"2026-01-14","f":5},{"g":"수원시 권선구","n":"수원하늘채더퍼스트2단지","a":60,"p":58000,"d":"2026-01-25","f":4},{"g":"수원시 권선구","n":"신안풍림","a":134,"p":58000,"d":"2026-01-08","f":11},{"g":"수원시 팔달구","n":"꽃뫼버들마을진흥","a":60,"p":58000,"d":"2026-01-26","f":6},{"g":"수원시 영통구","n":"벽적골9단지주공","a":59,"p":58000,"d":"2026-01-26","f":8},{"g":"성남시 수정구","n":"동인트루빌2","a":84,"p":58000,"d":"2026-01-26","f":3},{"g":"성남시 중원구","n":"이안모란센트럴파크","a":61,"p":58000,"d":"2026-01-16","f":13},{"g":"안양시 만안구","n":"코오롱하늘채","a":85,"p":58000,"d":"2026-01-24","f":3},{"g":"안양시 만안구","n":"아르테자이","a":50,"p":58000,"d":"2026-01-16","f":7},{"g":"안양시 만안구","n":"석수경남아너스빌","a":79,"p":58000,"d":"2026-01-11","f":12},{"g":"안양시 동안구","n":"평촌자이아이파크","a":46,"p":58000,"d":"2026-01-20","f":23},{"g":"안양시 동안구","n":"대광로제비앙","a":85,"p":58000,"d":"2026-01-05","f":23},{"g":"부천시 원미구","n":"백송마을(풍림아이원)","a":60,"p":58000,"d":"2026-01-16","f":6},{"g":"부천시 원미구","n":"포도마을(영남)","a":75,"p":58000,"d":"2026-01-07","f":1},{"g":"부천시 소사구","n":"일루미스테이트","a":60,"p":58000,"d":"2026-01-17","f":2},{"g":"부천시 소사구","n":"일루미스테이트","a":60,"p":58000,"d":"2026-01-15","f":7},{"g":"부천시 소사구","n":"일루미스테이트","a":60,"p":58000,"d":"2026-01-11","f":8},{"g":"부천시 소사구","n":"일루미스테이트","a":60,"p":58000,"d":"2026-01-17","f":15},{"g":"부천시 소사구","n":"푸르지오","a":85,"p":58000,"d":"2026-01-09","f":1},{"g":"광명시","n":"주공1","a":50,"p":58000,"d":"2026-01-22","f":11},{"g":"광명시","n":"동양메이저1차","a":85,"p":58000,"d":"2026-01-21","f":8},{"g":"평택시","n":"고덕국제신도시제일풍경채3차센텀","a":76,"p":58000,"d":"2026-01-31","f":6},{"g":"평택시","n":"고덕국제신도시파라곤에듀포레","a":85,"p":58000,"d":"2026-01-24","f":12},{"g":"평택시","n":"고덕국제신도시파라곤에듀포레","a":85,"p":58000,"d":"2026-01-18","f":17},{"g":"안산시 상록구","n":"안산고잔9차푸르지오","a":102,"p":58000,"d":"2026-01-05","f":14},{"g":"안산시 단원구","n":"호수마을풍림","a":143,"p":58000,"d":"2026-01-30","f":11},{"g":"안산시 단원구","n":"안산라프리모","a":85,"p":58000,"d":"2026-01-28","f":15},{"g":"안산시 단원구","n":"안산라프리모","a":85,"p":58000,"d":"2026-01-15","f":14},{"g":"고양시 덕양구","n":"서정센텀퍼스티지(서정마을4단지)","a":85,"p":58000,"d":"2026-01-16","f":6},{"g":"고양시 덕양구","n":"삼성래미안","a":85,"p":58000,"d":"2026-01-26","f":11},{"g":"고양시 덕양구","n":"지축나인포레","a":47,"p":58000,"d":"2026-01-21","f":17},{"g":"고양시 덕양구","n":"햇빛마을","a":100,"p":58000,"d":"2026-01-05","f":6},{"g":"고양시 일산서구","n":"일산푸르지오더센트럴","a":70,"p":58000,"d":"2026-01-17","f":32},{"g":"구리시","n":"아름마을엘지","a":85,"p":58000,"d":"2026-01-16","f":1},{"g":"구리시","n":"주공4-1","a":58,"p":58000,"d":"2026-01-29","f":7},{"g":"구리시","n":"주공4-2","a":60,"p":58000,"d":"2026-01-28","f":20},{"g":"구리시","n":"주공1","a":60,"p":58000,"d":"2026-01-24","f":6},{"g":"구리시","n":"아름마을삼성","a":60,"p":58000,"d":"2026-01-15","f":15},{"g":"구리시","n":"주공1","a":60,"p":58000,"d":"2026-01-12","f":4},{"g":"구리시","n":"아름마을일신","a":60,"p":58000,"d":"2026-01-09","f":8},{"g":"남양주시","n":"호평마을중흥에스-클래스로하스","a":133,"p":58000,"d":"2026-01-26","f":20},{"g":"남양주시","n":"덕소강변라온프라이빗","a":60,"p":58000,"d":"2026-01-18","f":3},{"g":"남양주시","n":"호평오네뜨센트럴","a":75,"p":58000,"d":"2026-01-21","f":16},{"g":"남양주시","n":"다산리버펠리체3단지","a":85,"p":58000,"d":"2026-01-10","f":17},{"g":"남양주시","n":"별내퍼스트포레","a":56,"p":58000,"d":"2026-01-17","f":8},{"g":"남양주시","n":"롯데낙천대","a":85,"p":58000,"d":"2026-01-15","f":17},{"g":"남양주시","n":"호평파라곤","a":131,"p":58000,"d":"2026-01-13","f":9},{"g":"오산시","n":"호반써밋라포레","a":85,"p":58000,"d":"2026-01-14","f":12},{"g":"시흥시","n":"시흥은계우미린레이크","a":85,"p":58000,"d":"2026-01-24","f":20},{"g":"시흥시","n":"한라비발디캠퍼스3차","a":85,"p":58000,"d":"2026-01-17","f":32},{"g":"군포시","n":"용호마을e-편한세상","a":85,"p":58000,"d":"2026-01-20","f":5},{"g":"하남시","n":"동원베네스트","a":85,"p":58000,"d":"2026-01-29","f":7},{"g":"하남시","n":"현대홈타운","a":81,"p":58000,"d":"2026-01-24","f":6},{"g":"하남시","n":"서해","a":85,"p":58000,"d":"2026-01-31","f":13},{"g":"하남시","n":"한솔리치빌(3단지)","a":60,"p":58000,"d":"2026-01-23","f":8},{"g":"용인시 처인구","n":"우미린센트럴파크","a":76,"p":58000,"d":"2026-01-28","f":7},{"g":"용인시 기흥구","n":"용인보라효성해링턴플레이스","a":75,"p":58000,"d":"2026-01-31","f":10},{"g":"용인시 기흥구","n":"교동마을마북2차이편한세상","a":122,"p":58000,"d":"2026-01-29","f":10},{"g":"용인시 기흥구","n":"하마비마을동부","a":135,"p":58000,"d":"2026-01-29","f":6},{"g":"용인시 기흥구","n":"신동백서해그랑블2차","a":85,"p":58000,"d":"2026-01-28","f":18},{"g":"용인시 기흥구","n":"신흥덕롯데캐슬레이시티","a":60,"p":58000,"d":"2026-01-14","f":32},{"g":"용인시 기흥구","n":"신흥덕롯데캐슬레이시티","a":60,"p":58000,"d":"2026-01-17","f":12},{"g":"용인시 기흥구","n":"코오롱하늘채(5단지)","a":103,"p":58000,"d":"2026-01-17","f":10},{"g":"용인시 기흥구","n":"신동백서해그랑블2차","a":85,"p":58000,"d":"2026-01-15","f":19},{"g":"용인시 기흥구","n":"초원마을성원상떼빌2차","a":130,"p":58000,"d":"2026-01-06","f":11},{"g":"용인시 기흥구","n":"구성우림필유","a":84,"p":58000,"d":"2026-01-12","f":10},{"g":"용인시 기흥구","n":"교동마을마북이편한세상","a":85,"p":58000,"d":"2026-01-03","f":15},{"g":"용인시 기흥구","n":"신동백서해그랑블2차","a":85,"p":58000,"d":"2026-01-10","f":15},{"g":"용인시 기흥구","n":"용인기흥효성해링턴플레이스","a":85,"p":58000,"d":"2026-01-10","f":5},{"g":"용인시 기흥구","n":"센트럴파크원","a":85,"p":58000,"d":"2026-01-08","f":1},{"g":"용인시 수지구","n":"동아아파트","a":60,"p":58000,"d":"2026-01-24","f":5},{"g":"용인시 수지구","n":"삼익아파트","a":60,"p":58000,"d":"2026-01-24","f":9},{"g":"용인시 수지구","n":"삼익아파트","a":60,"p":58000,"d":"2026-01-08","f":14},{"g":"용인시 수지구","n":"풍림아파트","a":60,"p":58000,"d":"2026-01-08","f":4},{"g":"용인시 수지구","n":"동문그린","a":60,"p":58000,"d":"2026-01-02","f":9},{"g":"파주시","n":"한빛마을9단지롯데캐슬1차","a":84,"p":58000,"d":"2026-01-31","f":17},{"g":"파주시","n":"초롱꽃마을13단지디에트르더퍼스트","a":60,"p":58000,"d":"2026-01-23","f":18},{"g":"파주시","n":"한빛마을9단지롯데캐슬1차","a":84,"p":58000,"d":"2026-01-09","f":17},{"g":"김포시","n":"힐스테이트 리버시티 2단지","a":77,"p":58000,"d":"2026-01-31","f":14},{"g":"김포시","n":"캐슬앤파밀리에시티 1단지","a":85,"p":58000,"d":"2026-01-24","f":6},{"g":"김포시","n":"캐슬앤파밀리에시티 1단지","a":85,"p":58000,"d":"2026-01-17","f":11},{"g":"김포시","n":"e편한세상캐널시티","a":84,"p":58000,"d":"2026-01-14","f":23},{"g":"화성시 효행구","n":"중흥에스클래스더센트럴","a":72,"p":58000,"d":"2026-01-16","f":14},{"g":"화성시 병점구","n":"e편한세상반월나노시티역","a":58,"p":58000,"d":"2026-01-28","f":23},{"g":"화성시 병점구","n":"서동탄역파크자이2차","a":85,"p":58000,"d":"2026-01-17","f":14},{"g":"화성시 동탄구","n":"동탄2하우스디더레이크","a":60,"p":58000,"d":"2026-01-10","f":8},{"g":"화성시 동탄구","n":"호반베르디움센트럴포레","a":85,"p":58000,"d":"2026-01-17","f":2},{"g":"화성시 동탄구","n":"동탄호수자이파밀리에","a":60,"p":58000,"d":"2026-01-29","f":1},{"g":"광주시","n":"광주태전아이파크","a":85,"p":58000,"d":"2026-01-04","f":13},{"g":"양평군","n":"더샵양평리버포레","a":85,"p":58000,"d":"2026-01-09","f":9},{"g":"중랑구","n":"건영2차아파트","a":57,"p":57900,"d":"2026-01-30","f":2},{"g":"노원구","n":"염광","a":59,"p":57900,"d":"2026-01-30","f":3},{"g":"노원구","n":"염광","a":59,"p":57900,"d":"2026-01-12","f":9},{"g":"마포구","n":"한화오벨리스크","a":39,"p":57900,"d":"2026-01-25","f":9},{"g":"성남시 분당구","n":"미켈란쉐르빌","a":41,"p":57900,"d":"2026-01-19","f":5},{"g":"화성시 병점구","n":"e편한세상반월나노시티역","a":59,"p":57900,"d":"2026-01-17","f":19},{"g":"노원구","n":"상계주공2(고층)","a":59,"p":57850,"d":"2026-01-07","f":15},{"g":"미추홀구","n":"인천 SK Sky VIEW","a":85,"p":57800,"d":"2026-01-24","f":7},{"g":"연수구","n":"송도풍림아이원1단지","a":85,"p":57800,"d":"2026-01-25","f":12},{"g":"연수구","n":"송도에듀포레푸르지오","a":60,"p":57800,"d":"2026-01-06","f":21},{"g":"서구","n":"검단신도시모아미래도엘리트파크","a":85,"p":57800,"d":"2026-01-31","f":13},{"g":"서구","n":"힐데스하임","a":60,"p":57800,"d":"2026-01-08","f":11},{"g":"수원시 장안구","n":"한일타운대림","a":85,"p":57800,"d":"2026-01-27","f":7},{"g":"수원시 권선구","n":"수원하늘채더퍼스트2단지","a":60,"p":57800,"d":"2026-01-04","f":9},{"g":"수원시 팔달구","n":"대한대우","a":85,"p":57800,"d":"2026-01-24","f":2},{"g":"수원시 팔달구","n":"꽃뫼버들마을진흥","a":60,"p":57800,"d":"2026-01-31","f":14},{"g":"안양시 동안구","n":"안양임곡휴먼시아","a":60,"p":57800,"d":"2026-01-07","f":6},{"g":"부천시 원미구","n":"백송마을(풍림아이원)","a":60,"p":57800,"d":"2026-01-16","f":14},{"g":"부천시 소사구","n":"일루미스테이트","a":60,"p":57800,"d":"2026-01-21","f":18},{"g":"부천시 소사구","n":"현대프라힐스소사역더프라임","a":75,"p":57800,"d":"2026-01-13","f":21},{"g":"고양시 덕양구","n":"삼송10단지동일스위트2차","a":66,"p":57800,"d":"2026-01-12","f":12},{"g":"구리시","n":"원일아름","a":85,"p":57800,"d":"2026-01-30","f":13},{"g":"하남시","n":"부영","a":50,"p":57800,"d":"2026-01-02","f":5},{"g":"용인시 처인구","n":"역북지웰푸르지오","a":85,"p":57800,"d":"2026-01-16","f":22},{"g":"용인시 처인구","n":"역북지웰푸르지오","a":85,"p":57800,"d":"2026-01-28","f":26},{"g":"용인시 기흥구","n":"구성우림필유","a":84,"p":57800,"d":"2026-01-29","f":5},{"g":"용인시 기흥구","n":"신흥덕롯데캐슬레이시티","a":60,"p":57800,"d":"2026-01-10","f":12},{"g":"용인시 기흥구","n":"신흥덕롯데캐슬레이시티","a":60,"p":57800,"d":"2026-01-03","f":16},{"g":"미추홀구","n":"인천 SK Sky VIEW","a":85,"p":57750,"d":"2026-01-24","f":4},{"g":"부평구","n":"부평SKVIEW해모로","a":75,"p":57750,"d":"2026-01-13","f":1},{"g":"의정부시","n":"의정부롯데캐슬골드파크2단지","a":85,"p":57750,"d":"2026-01-02","f":25},{"g":"고양시 일산서구","n":"하이파크시티일산파밀리에2단지","a":147,"p":57750,"d":"2026-01-23","f":16},{"g":"노원구","n":"상계주공11(고층)","a":58,"p":57700,"d":"2026-01-24","f":15},{"g":"구로구","n":"신개봉삼환","a":60,"p":57700,"d":"2026-01-19","f":8},{"g":"안산시 단원구","n":"주공그린빌8","a":84,"p":57700,"d":"2026-01-24","f":9},{"g":"시흥시","n":"시흥센트럴푸르지오","a":60,"p":57700,"d":"2026-01-31","f":8},{"g":"의왕시","n":"한진해모로","a":85,"p":57700,"d":"2026-01-15","f":10},{"g":"화성시 병점구","n":"에스케이뷰파크2차","a":85,"p":57700,"d":"2026-01-13","f":11},{"g":"화성시 동탄구","n":"푸르지오","a":58,"p":57700,"d":"2026-01-23","f":20},{"g":"화성시 동탄구","n":"동탄역 신미주","a":85,"p":57700,"d":"2026-01-09","f":11},{"g":"연수구","n":"e편한세상송도","a":71,"p":57600,"d":"2026-01-24","f":32},{"g":"안양시 만안구","n":"벽산","a":71,"p":57600,"d":"2026-01-26","f":11},{"g":"안산시 단원구","n":"대우푸르지오5","a":85,"p":57600,"d":"2026-01-10","f":15},{"g":"광진구","n":"에이탑","a":73,"p":57500,"d":"2026-01-16","f":6},{"g":"노원구","n":"상계주공12(고층)","a":62,"p":57500,"d":"2026-01-18","f":15},{"g":"노원구","n":"태강아파트(아이파크)","a":50,"p":57500,"d":"2026-01-25","f":13},{"g":"노원구","n":"태강아파트(아이파크)","a":50,"p":57500,"d":"2026-01-24","f":13},{"g":"노원구","n":"주공8","a":50,"p":57500,"d":"2026-01-15","f":12},{"g":"노원구","n":"상계주공4(고층)","a":58,"p":57500,"d":"2026-01-14","f":1},{"g":"은평구","n":"펠리시티","a":56,"p":57500,"d":"2026-01-09","f":7},{"g":"구로구","n":"청구","a":60,"p":57500,"d":"2026-01-05","f":12},{"g":"중구","n":"스카이시티자이","a":99,"p":57500,"d":"2026-01-23","f":15},{"g":"연수구","n":"송도에듀포레푸르지오","a":60,"p":57500,"d":"2026-01-05","f":4},{"g":"부평구","n":"부평SKVIEW해모로","a":60,"p":57500,"d":"2026-01-22","f":17},{"g":"부평구","n":"부평신일해피트리더루츠","a":75,"p":57500,"d":"2026-01-12","f":3},{"g":"계양구","n":"계양한양수자인","a":85,"p":57500,"d":"2026-01-27","f":10},{"g":"서구","n":"검단신안인스빌어반퍼스트","a":95,"p":57500,"d":"2026-01-23","f":9},{"g":"서구","n":"검단신도시디에트르더힐","a":76,"p":57500,"d":"2026-01-23","f":8},{"g":"서구","n":"검단신도시디에트르더힐","a":76,"p":57500,"d":"2026-01-10","f":15},{"g":"수원시 권선구","n":"쌍용더플래티넘오목천역","a":60,"p":57500,"d":"2026-01-14","f":13},{"g":"수원시 팔달구","n":"꽃뫼버들마을진흥","a":60,"p":57500,"d":"2026-01-16","f":13},{"g":"성남시 수정구","n":"진로","a":60,"p":57500,"d":"2026-01-22","f":2},{"g":"의정부시","n":"장암더샵포레스트","a":84,"p":57500,"d":"2026-01-14","f":7},{"g":"부천시 원미구","n":"대림e-편한세상1차","a":85,"p":57500,"d":"2026-01-13","f":10},{"g":"부천시 원미구","n":"무지개마을(LG)","a":85,"p":57500,"d":"2026-01-07","f":8},{"g":"안산시 상록구","n":"엘리지움","a":182,"p":57500,"d":"2026-01-02","f":2},{"g":"안산시 단원구","n":"e편한세상초지역센트럴포레","a":60,"p":57500,"d":"2026-01-27","f":12},{"g":"안산시 단원구","n":"대우푸르지오5","a":85,"p":57500,"d":"2026-01-20","f":14},{"g":"안산시 단원구","n":"안산라프리모","a":85,"p":57500,"d":"2026-01-20","f":7},{"g":"고양시 덕양구","n":"별빛마을9단지(901동에서906동)","a":85,"p":57500,"d":"2026-01-22","f":12},{"g":"고양시 덕양구","n":"삼송10단지동일스위트2차","a":66,"p":57500,"d":"2026-01-12","f":25},{"g":"고양시 일산동구","n":"위시티블루밍3단지","a":102,"p":57500,"d":"2026-01-30","f":22},{"g":"고양시 일산서구","n":"후곡마을(금호)","a":84,"p":57500,"d":"2026-01-24","f":15},{"g":"구리시","n":"대림한숲","a":52,"p":57500,"d":"2026-01-31","f":2},{"g":"구리시","n":"주공1","a":60,"p":57500,"d":"2026-01-22","f":4},{"g":"구리시","n":"원일아름","a":85,"p":57500,"d":"2026-01-26","f":23},{"g":"구리시","n":"토평주공","a":60,"p":57500,"d":"2026-01-10","f":6},{"g":"남양주시","n":"동부센트레빌","a":85,"p":57500,"d":"2026-01-24","f":9},{"g":"군포시","n":"대원칸타빌(103동)","a":129,"p":57500,"d":"2026-01-03","f":7},{"g":"의왕시","n":"모락산현대","a":79,"p":57500,"d":"2026-01-11","f":18},{"g":"용인시 기흥구","n":"용인보라효성해링턴플레이스","a":75,"p":57500,"d":"2026-01-29","f":22},{"g":"용인시 기흥구","n":"신흥덕롯데캐슬레이시티","a":60,"p":57500,"d":"2026-01-10","f":6},{"g":"용인시 기흥구","n":"신동백서해그랑블2차","a":85,"p":57500,"d":"2026-01-07","f":16},{"g":"용인시 기흥구","n":"신흥덕롯데캐슬레이시티","a":60,"p":57500,"d":"2026-01-02","f":15},{"g":"용인시 수지구","n":"도담마을죽전파크빌","a":60,"p":57500,"d":"2026-01-14","f":5},{"g":"파주시","n":"파주운정신도시디에트르에듀타운","a":85,"p":57500,"d":"2026-01-02","f":10},{"g":"화성시 병점구","n":"에스케이뷰파크","a":85,"p":57500,"d":"2026-01-12","f":1},{"g":"화성시 동탄구","n":"더레이크시티부영1단지","a":60,"p":57500,"d":"2026-01-31","f":12},{"g":"화성시 동탄구","n":"동탄숲속마을자연앤경남아너스빌(1124-0)","a":85,"p":57500,"d":"2026-01-25","f":16},{"g":"화성시 동탄구","n":"포스코더샵2차","a":84,"p":57500,"d":"2026-01-17","f":23},{"g":"화성시 동탄구","n":"포스코더샵2차","a":85,"p":57500,"d":"2026-01-12","f":6},{"g":"서구","n":"검단신도시파라곤보타닉파크","a":85,"p":57400,"d":"2026-01-19","f":6},{"g":"수원시 권선구","n":"권선자이e편한세상","a":60,"p":57400,"d":"2026-01-19","f":11},{"g":"구리시","n":"아름마을삼성","a":60,"p":57400,"d":"2026-01-12","f":5},{"g":"의왕시","n":"충무","a":102,"p":57400,"d":"2026-01-29","f":13},{"g":"화성시 동탄구","n":"동탄숲속마을자연앤경남아너스빌(1115-0)","a":77,"p":57400,"d":"2026-01-05","f":17},{"g":"양평군","n":"센트럴파크써밋","a":80,"p":57400,"d":"2026-01-28","f":18},{"g":"미추홀구","n":"포레나미추홀","a":85,"p":57300,"d":"2026-01-12","f":15},{"g":"부평구","n":"힐스테이트부평","a":60,"p":57300,"d":"2026-01-18","f":17},{"g":"서구","n":"검단신도시모아미래도엘리트파크","a":85,"p":57300,"d":"2026-01-24","f":18},{"g":"서구","n":"호반베르디움(116-6)","a":85,"p":57300,"d":"2026-01-02","f":11},{"g":"수원시 영통구","n":"벽적골9단지주공","a":59,"p":57300,"d":"2026-01-19","f":13},{"g":"안양시 동안구","n":"더포레스트힐","a":85,"p":57300,"d":"2026-01-12","f":14},{"g":"안산시 단원구","n":"서해그랑블","a":99,"p":57300,"d":"2026-01-02","f":7},{"g":"구리시","n":"주공4-2","a":60,"p":57300,"d":"2026-01-31","f":3},{"g":"화성시 효행구","n":"중흥에스클래스더센트럴","a":73,"p":57300,"d":"2026-01-29","f":19},{"g":"광주시","n":"광주태전아이파크","a":85,"p":57300,"d":"2026-01-03","f":21},{"g":"노원구","n":"중계그린1단지","a":50,"p":57200,"d":"2026-01-12","f":3},{"g":"부평구","n":"부평캐슬&더샵퍼스트","a":60,"p":57200,"d":"2026-01-06","f":24},{"g":"서구","n":"검단신도시모아미래도엘리트파크","a":85,"p":57200,"d":"2026-01-14","f":5},{"g":"성남시 수정구","n":"양우내안애","a":74,"p":57200,"d":"2026-01-20","f":1},{"g":"고양시 덕양구","n":"햇빛마을21단지","a":135,"p":57200,"d":"2026-01-15","f":14},{"g":"시흥시","n":"장현호반써밋","a":85,"p":57200,"d":"2026-01-12","f":11},{"g":"용인시 기흥구","n":"기흥파크뷰","a":85,"p":57200,"d":"2026-01-28","f":12},{"g":"중랑구","n":"중랑숲리가","a":60,"p":57000,"d":"2026-01-15","f":1},{"g":"중랑구","n":"중랑숲리가","a":60,"p":57000,"d":"2026-01-15","f":1},{"g":"중랑구","n":"화성.두산아파트","a":67,"p":57000,"d":"2026-01-09","f":1},{"g":"강북구","n":"벽산라이브파크","a":60,"p":57000,"d":"2026-01-27","f":1},{"g":"도봉구","n":"수산트리플","a":60,"p":57000,"d":"2026-01-22","f":12},{"g":"도봉구","n":"한신","a":85,"p":57000,"d":"2026-01-21","f":7},{"g":"노원구","n":"상계주공4(고층)","a":58,"p":57000,"d":"2026-01-28","f":15},{"g":"노원구","n":"상계주공10(고층)","a":59,"p":57000,"d":"2026-01-17","f":1},{"g":"노원구","n":"상계주공9(고층)","a":62,"p":57000,"d":"2026-01-22","f":15},{"g":"노원구","n":"상계신동아","a":85,"p":57000,"d":"2026-01-26","f":12},{"g":"노원구","n":"중계그린1단지","a":50,"p":57000,"d":"2026-01-13","f":5},{"g":"노원구","n":"중계그린1단지","a":50,"p":57000,"d":"2026-01-13","f":4},{"g":"노원구","n":"상아","a":51,"p":57000,"d":"2026-01-07","f":9},{"g":"서대문구","n":"풍림2","a":58,"p":57000,"d":"2026-01-05","f":2},{"g":"강서구","n":"방화그린","a":50,"p":57000,"d":"2026-01-13","f":11},{"g":"금천구","n":"벽산","a":115,"p":57000,"d":"2026-01-27","f":18},{"g":"금천구","n":"금천현대","a":60,"p":57000,"d":"2026-01-21","f":5},{"g":"관악구","n":"관악산휴먼시아1단지","a":60,"p":57000,"d":"2026-01-06","f":2},{"g":"강동구","n":"파크프라자","a":58,"p":57000,"d":"2026-01-17","f":4},{"g":"미추홀구","n":"포레나미추홀","a":77,"p":57000,"d":"2026-01-17","f":19},{"g":"연수구","n":"송도오션파크베르디움","a":76,"p":57000,"d":"2026-01-26","f":11},{"g":"연수구","n":"송도풍림아이원2단지","a":85,"p":57000,"d":"2026-01-23","f":4},{"g":"연수구","n":"베르디움더퍼스트","a":64,"p":57000,"d":"2026-01-26","f":1},{"g":"연수구","n":"송도풍림아이원3단지","a":85,"p":57000,"d":"2026-01-17","f":15},{"g":"연수구","n":"베르디움더퍼스트","a":64,"p":57000,"d":"2026-01-03","f":25},{"g":"남동구","n":"구월유승한내들퍼스티지","a":94,"p":57000,"d":"2026-01-31","f":29},{"g":"남동구","n":"구월유승한내들퍼스티지","a":84,"p":57000,"d":"2026-01-24","f":11},{"g":"남동구","n":"에코메트로5","a":85,"p":57000,"d":"2026-01-21","f":9},{"g":"부평구","n":"브라운스톤부평","a":73,"p":57000,"d":"2026-01-29","f":12},{"g":"부평구","n":"더샵부평센트럴시티","a":69,"p":57000,"d":"2026-01-23","f":36},{"g":"부평구","n":"부평캐슬&더샵퍼스트","a":60,"p":57000,"d":"2026-01-14","f":24},{"g":"서구","n":"우미린더헤리티지","a":60,"p":57000,"d":"2026-01-27","f":20},{"g":"서구","n":"청라힐스테이트","a":85,"p":57000,"d":"2026-01-24","f":7},{"g":"서구","n":"가재울역트루엘에코시티","a":85,"p":57000,"d":"2026-01-09","f":29},{"g":"서구","n":"검단신도시디에트르더펠리체","a":85,"p":57000,"d":"2026-01-05","f":13},{"g":"수원시 장안구","n":"수원장안힐스테이트","a":60,"p":57000,"d":"2026-01-19","f":16},{"g":"수원시 권선구","n":"수원아이파크시티7단지","a":60,"p":57000,"d":"2026-01-31","f":9},{"g":"수원시 권선구","n":"호매실더센트라고","a":85,"p":57000,"d":"2026-01-26","f":15},{"g":"수원시 권선구","n":"수원아이파크시티5단지","a":75,"p":57000,"d":"2026-01-17","f":3},{"g":"수원시 권선구","n":"수원아이파크시티7단지","a":60,"p":57000,"d":"2026-01-08","f":10},{"g":"수원시 권선구","n":"쌍용더플래티넘오목천역","a":60,"p":57000,"d":"2026-01-06","f":8},{"g":"수원시 권선구","n":"수원역센트럴어반시티아파트(수원센트럴타운3단지)","a":85,"p":57000,"d":"2026-01-03","f":4},{"g":"수원시 팔달구","n":"수원인계동동문굿모닝힐아파트","a":64,"p":57000,"d":"2026-01-27","f":23},{"g":"수원시 영통구","n":"e편한세상영통2차(1단지)","a":60,"p":57000,"d":"2026-01-28","f":13},{"g":"수원시 영통구","n":"동수원자이1차","a":85,"p":57000,"d":"2026-01-23","f":5},{"g":"수원시 영통구","n":"주공","a":67,"p":57000,"d":"2026-01-19","f":5},{"g":"성남시 중원구","n":"은빛마을(두산위브)","a":57,"p":57000,"d":"2026-01-15","f":4},{"g":"의정부시","n":"I-PARK","a":85,"p":57000,"d":"2026-01-26","f":18},{"g":"의정부시","n":"탑석센트럴자이","a":60,"p":57000,"d":"2026-01-23","f":29},{"g":"의정부시","n":"의정부역푸르지오더센트럴","a":60,"p":57000,"d":"2026-01-10","f":24},{"g":"의정부시","n":"고산수자인디에스티지아트포레","a":80,"p":57000,"d":"2026-01-08","f":15},{"g":"안양시 만안구","n":"주공그린빌","a":60,"p":57000,"d":"2026-01-26","f":4},{"g":"안양시 만안구","n":"현대아파트","a":60,"p":57000,"d":"2026-01-18","f":20},{"g":"안양시 동안구","n":"HHI브라운빌3차","a":85,"p":57000,"d":"2026-01-10","f":5},{"g":"안양시 동안구","n":"호계임광그대가3차","a":85,"p":57000,"d":"2026-01-26","f":14},{"g":"안양시 동안구","n":"호계2차현대홈타운","a":60,"p":57000,"d":"2026-01-13","f":12},{"g":"부천시 원미구","n":"부천아이파크","a":60,"p":57000,"d":"2026-01-24","f":18},{"g":"부천시 원미구","n":"사랑마을(청구)","a":102,"p":57000,"d":"2026-01-17","f":14},{"g":"부천시 원미구","n":"중동대림","a":85,"p":57000,"d":"2026-01-13","f":6},{"g":"부천시 소사구","n":"옥길센트리뷰","a":60,"p":57000,"d":"2026-01-03","f":10},{"g":"부천시 소사구","n":"소사에스케이뷰","a":85,"p":57000,"d":"2026-01-15","f":5},{"g":"광명시","n":"주공5","a":58,"p":57000,"d":"2026-01-26","f":5},{"g":"광명시","n":"영화아이닉스","a":79,"p":57000,"d":"2026-01-12","f":11},{"g":"광명시","n":"주공1","a":50,"p":57000,"d":"2026-01-06","f":5},{"g":"평택시","n":"고덕국제신도시제일풍경채","a":85,"p":57000,"d":"2026-01-24","f":13},{"g":"평택시","n":"호반써밋고덕국제신도시에듀파크","a":85,"p":57000,"d":"2026-01-19","f":10},{"g":"평택시","n":"신영평택비전지웰푸르지오","a":85,"p":57000,"d":"2026-01-18","f":14},{"g":"안산시 상록구","n":"안산고잔6차푸르지오","a":89,"p":57000,"d":"2026-01-21","f":7},{"g":"안산시 상록구","n":"안산고잔9차푸르지오","a":102,"p":57000,"d":"2026-01-07","f":6},{"g":"안산시 단원구","n":"안산라프리모","a":85,"p":57000,"d":"2026-01-20","f":20},{"g":"안산시 단원구","n":"안산라프리모","a":85,"p":57000,"d":"2026-01-06","f":3},{"g":"안산시 단원구","n":"호수마을풍림","a":102,"p":57000,"d":"2026-01-03","f":15},{"g":"고양시 덕양구","n":"삼송2차아이파크","a":75,"p":57000,"d":"2026-01-14","f":2},{"g":"고양시 일산서구","n":"일산두산위브더제니스","a":96,"p":57000,"d":"2026-01-27","f":14},{"g":"구리시","n":"럭키","a":59,"p":57000,"d":"2026-01-23","f":7},{"g":"구리시","n":"우방아이유쉘","a":85,"p":57000,"d":"2026-01-26","f":14},{"g":"구리시","n":"럭키","a":59,"p":57000,"d":"2026-01-19","f":10},{"g":"구리시","n":"건영","a":84,"p":57000,"d":"2026-01-15","f":3},{"g":"구리시","n":"토평주공","a":60,"p":57000,"d":"2026-01-16","f":7},{"g":"구리시","n":"수택주공","a":60,"p":57000,"d":"2026-01-14","f":22},{"g":"남양주시","n":"덕소쌍용","a":135,"p":57000,"d":"2026-01-26","f":6},{"g":"남양주시","n":"롯데낙천대","a":85,"p":57000,"d":"2026-01-29","f":3},{"g":"남양주시","n":"평내마을금호어울림","a":124,"p":57000,"d":"2026-01-08","f":8},{"g":"남양주시","n":"부영사랑으로","a":85,"p":57000,"d":"2026-01-12","f":4},{"g":"남양주시","n":"신별내퇴계원어울림","a":85,"p":57000,"d":"2026-01-03","f":17},{"g":"시흥시","n":"한라비발디캠퍼스3차","a":85,"p":57000,"d":"2026-01-16","f":36},{"g":"시흥시","n":"은계브리즈힐","a":84,"p":57000,"d":"2026-01-08","f":10},{"g":"시흥시","n":"호반베르디움센트로하임","a":85,"p":57000,"d":"2026-01-03","f":22},{"g":"군포시","n":"주공3(886)","a":85,"p":57000,"d":"2026-01-31","f":24},{"g":"군포시","n":"의왕역센트럴시티(휴먼시아3단지)","a":85,"p":57000,"d":"2026-01-23","f":3},{"g":"용인시 처인구","n":"용인고림양우내안愛더센트럴","a":76,"p":57000,"d":"2026-01-23","f":23},{"g":"용인시 처인구","n":"역북지웰푸르지오","a":85,"p":57000,"d":"2026-01-15","f":25},{"g":"용인시 기흥구","n":"교동마을현대홈타운","a":124,"p":57000,"d":"2026-01-31","f":10},{"g":"용인시 기흥구","n":"호수마을자연앤데시앙","a":85,"p":57000,"d":"2026-01-11","f":8},{"g":"용인시 기흥구","n":"신동백서해그랑블2차","a":85,"p":57000,"d":"2026-01-31","f":7},{"g":"용인시 기흥구","n":"하마비마을동부센트레빌","a":126,"p":57000,"d":"2026-01-26","f":6},{"g":"용인시 기흥구","n":"하마비마을동부센트레빌","a":85,"p":57000,"d":"2026-01-22","f":15},{"g":"용인시 수지구","n":"삼익아파트","a":60,"p":57000,"d":"2026-01-30","f":3},{"g":"용인시 수지구","n":"동아아파트","a":60,"p":57000,"d":"2026-01-20","f":5},{"g":"용인시 수지구","n":"도담마을죽전파크빌","a":60,"p":57000,"d":"2026-01-19","f":8},{"g":"용인시 수지구","n":"용인 죽전 효성해링턴 플레이스","a":60,"p":57000,"d":"2026-01-17","f":9},{"g":"용인시 수지구","n":"도담마을7단지뜨리에체","a":60,"p":57000,"d":"2026-01-05","f":16},{"g":"파주시","n":"초롱꽃마을6단지금강펜테리움","a":85,"p":57000,"d":"2026-01-24","f":10},{"g":"김포시","n":"힐스테이트 리버시티 2단지","a":77,"p":57000,"d":"2026-01-31","f":19},{"g":"김포시","n":"한강메트로자이1단지","a":74,"p":57000,"d":"2026-01-19","f":20},{"g":"김포시","n":"풍무자이1단지","a":134,"p":57000,"d":"2026-01-22","f":10},{"g":"화성시 만세구","n":"송산그린시티6차NOBLELAND스타빌리지","a":85,"p":57000,"d":"2026-01-29","f":9},{"g":"화성시 만세구","n":"신영지웰","a":118,"p":57000,"d":"2026-01-11","f":11},{"g":"화성시 만세구","n":"송산신도시대방노블랜드더퍼스티지1차","a":85,"p":57000,"d":"2026-01-12","f":22},{"g":"화성시 병점구","n":"e편한세상반월나노시티역","a":58,"p":57000,"d":"2026-01-20","f":22},{"g":"화성시 병점구","n":"e편한세상반월나노시티역","a":59,"p":57000,"d":"2026-01-31","f":19},{"g":"화성시 동탄구","n":"동탄역포레너스","a":60,"p":57000,"d":"2026-01-31","f":12},{"g":"화성시 동탄구","n":"동탄2신도시호반베르디움22단지","a":53,"p":57000,"d":"2026-01-29","f":22},{"g":"화성시 동탄구","n":"동탄숲속마을자연앤경남아너스빌(1115-0)","a":77,"p":57000,"d":"2026-01-09","f":22},{"g":"화성시 동탄구","n":"레이크힐 반도유보라 아이비파크 10.2","a":97,"p":57000,"d":"2026-01-07","f":11},{"g":"광주시","n":"힐스테이트초월역2블록","a":85,"p":57000,"d":"2026-01-02","f":5},{"g":"광주시","n":"이편한세상태재2단지","a":75,"p":57000,"d":"2026-01-06","f":7},{"g":"은평구","n":"미성","a":64,"p":56900,"d":"2026-01-18","f":10},{"g":"연수구","n":"e편한세상송도","a":71,"p":56900,"d":"2026-01-19","f":38},{"g":"부평구","n":"쌍용더플래티넘부평","a":73,"p":56900,"d":"2026-01-31","f":11},{"g":"서구","n":"우미린더헤리티지","a":60,"p":56900,"d":"2026-01-24","f":16},{"g":"의정부시","n":"의정부역푸르지오더센트럴","a":60,"p":56900,"d":"2026-01-31","f":28},{"g":"부천시 원미구","n":"부천아이파크","a":60,"p":56900,"d":"2026-01-30","f":10},{"g":"구리시","n":"한진","a":85,"p":56900,"d":"2026-01-10","f":5},{"g":"시흥시","n":"시흥은계우미린레이크","a":85,"p":56900,"d":"2026-01-12","f":16},{"g":"용인시 기흥구","n":"서천2차IPARK","a":75,"p":56900,"d":"2026-01-21","f":7},{"g":"파주시","n":"파주운정신도시디에트르더클래스아파트","a":85,"p":56900,"d":"2026-01-31","f":10},{"g":"김포시","n":"풍무푸르지오센트레빌","a":60,"p":56900,"d":"2026-01-10","f":20},{"g":"수원시 권선구","n":"센트라우스","a":60,"p":56850,"d":"2026-01-05","f":11},{"g":"도봉구","n":"금호2","a":84,"p":56800,"d":"2026-01-16","f":9},{"g":"노원구","n":"신일","a":85,"p":56800,"d":"2026-01-28","f":19},{"g":"노원구","n":"대동","a":60,"p":56800,"d":"2026-01-18","f":9},{"g":"연수구","n":"e편한세상송도","a":71,"p":56800,"d":"2026-01-31","f":12},{"g":"연수구","n":"e편한세상송도","a":71,"p":56800,"d":"2026-01-17","f":23},{"g":"부평구","n":"부평캐슬&더샵퍼스트","a":60,"p":56800,"d":"2026-01-22","f":22},{"g":"서구","n":"검단힐스테이트4차","a":107,"p":56800,"d":"2026-01-17","f":5},{"g":"서구","n":"검단신도시대방디에트르리버파크","a":60,"p":56800,"d":"2026-01-19","f":14},{"g":"수원시 권선구","n":"호매실역서희스타힐스","a":85,"p":56800,"d":"2026-01-30","f":4},{"g":"수원시 권선구","n":"수원아이파크시티7단지","a":60,"p":56800,"d":"2026-01-28","f":4},{"g":"안양시 동안구","n":"공작럭키","a":50,"p":56800,"d":"2026-01-22","f":14},{"g":"부천시 원미구","n":"미리내마을(롯데2)","a":64,"p":56800,"d":"2026-01-25","f":14},{"g":"부천시 소사구","n":"부천한신더휴메트로","a":60,"p":56800,"d":"2026-01-10","f":25},{"g":"구리시","n":"주공6","a":60,"p":56800,"d":"2026-01-23","f":4},{"g":"시흥시","n":"은계브리즈힐","a":85,"p":56800,"d":"2026-01-27","f":16},{"g":"용인시 기흥구","n":"쌍용스윗닷홈1","a":164,"p":56800,"d":"2026-01-19","f":12},{"g":"파주시","n":"한울마을1단지운정신도시IPARK","a":60,"p":56800,"d":"2026-01-30","f":12},{"g":"김포시","n":"풍무푸르지오센트레빌","a":60,"p":56800,"d":"2026-01-24","f":10},{"g":"화성시 효행구","n":"중흥에스클래스더센트럴","a":72,"p":56800,"d":"2026-01-24","f":3},{"g":"화성시 병점구","n":"서동탄역파크자이","a":85,"p":56800,"d":"2026-01-13","f":8},{"g":"화성시 동탄구","n":"산척동,동탄호수공원금강펜테리움센트럴파크Ⅱ","a":85,"p":56800,"d":"2026-01-05","f":4},{"g":"구리시","n":"인창이편한세상","a":60,"p":56750,"d":"2026-01-31","f":20},{"g":"파주시","n":"초롱꽃마을6단지금강펜테리움","a":85,"p":56750,"d":"2026-01-27","f":4},{"g":"도봉구","n":"성원","a":85,"p":56700,"d":"2026-01-14","f":11},{"g":"노원구","n":"상계주공1(고층)","a":59,"p":56700,"d":"2026-01-15","f":6},{"g":"부평구","n":"더샵부평센트럴시티","a":69,"p":56700,"d":"2026-01-22","f":43},{"g":"서구","n":"청라웰카운티 2차","a":97,"p":56700,"d":"2026-01-22","f":16},{"g":"서구","n":"루원시티 대성베르힐","a":85,"p":56700,"d":"2026-01-31","f":13},{"g":"수원시 장안구","n":"한일타운대림","a":85,"p":56700,"d":"2026-01-30","f":16},{"g":"수원시 장안구","n":"벽산블루밍","a":127,"p":56700,"d":"2026-01-27","f":13},{"g":"수원시 팔달구","n":"화서주공5단지","a":50,"p":56700,"d":"2026-01-29","f":17},{"g":"안양시 만안구","n":"안양명학역유보라더스마트","a":60,"p":56700,"d":"2026-01-04","f":15},{"g":"고양시 덕양구","n":"고양삼송동일스위트파크뷰7(1차)","a":66,"p":56700,"d":"2026-01-31","f":10},{"g":"고양시 일산서구","n":"일산두산위브더제니스","a":96,"p":56700,"d":"2026-01-23","f":16},{"g":"구리시","n":"주공4-2","a":60,"p":56700,"d":"2026-01-05","f":18},{"g":"용인시 기흥구","n":"한양수자인","a":89,"p":56700,"d":"2026-01-14","f":1},{"g":"화성시 병점구","n":"e편한세상반월나노시티역","a":59,"p":56700,"d":"2026-01-16","f":9},{"g":"화성시 동탄구","n":"동탄숲속마을자연앤경남아너스빌(1115-0)","a":76,"p":56700,"d":"2026-01-31","f":14},{"g":"광주시","n":"이편한세상태전2차(101~106동)","a":85,"p":56700,"d":"2026-01-13","f":15},{"g":"성남시 중원구","n":"비제이위채","a":85,"p":56600,"d":"2026-01-09","f":2},{"g":"중랑구","n":"신내","a":60,"p":56500,"d":"2026-01-29","f":10},{"g":"성북구","n":"우방","a":85,"p":56500,"d":"2026-01-27","f":4},{"g":"노원구","n":"대동","a":60,"p":56500,"d":"2026-01-18","f":12},{"g":"구로구","n":"한일유앤아이","a":60,"p":56500,"d":"2026-01-22","f":17},{"g":"구로구","n":"한일유앤아이","a":60,"p":56500,"d":"2026-01-21","f":7},{"g":"미추홀구","n":"인천 SK Sky VIEW","a":85,"p":56500,"d":"2026-01-31","f":26},{"g":"미추홀구","n":"인천 SK Sky VIEW","a":85,"p":56500,"d":"2026-01-27","f":9},{"g":"미추홀구","n":"포레나미추홀","a":85,"p":56500,"d":"2026-01-23","f":27},{"g":"연수구","n":"성지리벨루스","a":85,"p":56500,"d":"2026-01-26","f":5},{"g":"연수구","n":"더샵송도마리나베이","a":84,"p":56500,"d":"2026-01-23","f":1},{"g":"남동구","n":"간석래미안자이","a":85,"p":56500,"d":"2026-01-29","f":20},{"g":"남동구","n":"임광그대가","a":135,"p":56500,"d":"2026-01-18","f":10},{"g":"서구","n":"청라동양엔파트","a":119,"p":56500,"d":"2026-01-09","f":12},{"g":"수원시 권선구","n":"코오롱하늘채","a":85,"p":56500,"d":"2026-01-08","f":6},{"g":"수원시 권선구","n":"호매실역서희스타힐스","a":85,"p":56500,"d":"2026-01-14","f":5},{"g":"수원시 팔달구","n":"꽃뫼버들마을엘지","a":85,"p":56500,"d":"2026-01-29","f":8},{"g":"수원시 영통구","n":"e편한세상영통2차(1단지)","a":60,"p":56500,"d":"2026-01-30","f":18},{"g":"수원시 영통구","n":"벽적골9단지주공","a":59,"p":56500,"d":"2026-01-09","f":15},{"g":"성남시 중원구","n":"한빛스위티","a":81,"p":56500,"d":"2026-01-30","f":2},{"g":"의정부시","n":"탑석센트럴자이","a":60,"p":56500,"d":"2026-01-31","f":18},{"g":"의정부시","n":"의정부롯데캐슬골드파크2단지","a":85,"p":56500,"d":"2026-01-21","f":7},{"g":"의정부시","n":"장암더샵포레스트","a":85,"p":56500,"d":"2026-01-16","f":11},{"g":"안양시 만안구","n":"주공그린빌","a":60,"p":56500,"d":"2026-01-24","f":5},{"g":"부천시 원미구","n":"제이그랑블아파트","a":63,"p":56500,"d":"2026-01-31","f":5},{"g":"부천시 원미구","n":"연화마을(쌍용)","a":85,"p":56500,"d":"2026-01-31","f":4},{"g":"부천시 원미구","n":"미리내마을(롯데2)","a":72,"p":56500,"d":"2026-01-28","f":8},{"g":"부천시 소사구","n":"주공뜨란채","a":85,"p":56500,"d":"2026-01-25","f":13},{"g":"광명시","n":"우성","a":54,"p":56500,"d":"2026-01-17","f":12},{"g":"광명시","n":"주공1","a":50,"p":56500,"d":"2026-01-06","f":10},{"g":"평택시","n":"평택센트럴자이3단지","a":99,"p":56500,"d":"2026-01-17","f":5},{"g":"안산시 단원구","n":"호수공원(대림1)","a":87,"p":56500,"d":"2026-01-29","f":4},{"g":"안산시 단원구","n":"호수공원(대림1)","a":87,"p":56500,"d":"2026-01-13","f":5},{"g":"고양시 덕양구","n":"은빛마을(신성)5","a":135,"p":56500,"d":"2026-01-19","f":10},{"g":"고양시 덕양구","n":"별빛마을9단지(913동에서918동)","a":85,"p":56500,"d":"2026-01-31","f":7},{"g":"고양시 덕양구","n":"삼성래미안","a":60,"p":56500,"d":"2026-01-23","f":14},{"g":"고양시 덕양구","n":"한라비발디","a":85,"p":56500,"d":"2026-01-05","f":19},{"g":"구리시","n":"건영","a":84,"p":56500,"d":"2026-01-14","f":4},{"g":"구리시","n":"인창이편한세상","a":60,"p":56500,"d":"2026-01-24","f":7},{"g":"구리시","n":"아름마을삼성","a":60,"p":56500,"d":"2026-01-10","f":17},{"g":"남양주시","n":"별내퍼스트포레","a":56,"p":56500,"d":"2026-01-03","f":16},{"g":"시흥시","n":"목감퍼스트리움","a":60,"p":56500,"d":"2026-01-23","f":15},{"g":"시흥시","n":"호반베르디움더프라임","a":84,"p":56500,"d":"2026-01-04","f":8},{"g":"시흥시","n":"호반베르디움더프라임","a":84,"p":56500,"d":"2026-01-01","f":4},{"g":"군포시","n":"삼성마을시티프라디움(3단지)","a":85,"p":56500,"d":"2026-01-31","f":5},{"g":"군포시","n":"주공11","a":58,"p":56500,"d":"2026-01-31","f":12},{"g":"의왕시","n":"모락산현대","a":79,"p":56500,"d":"2026-01-09","f":14},{"g":"용인시 기흥구","n":"교동마을마북이편한세상","a":85,"p":56500,"d":"2026-01-26","f":7},{"g":"용인시 기흥구","n":"용인보라효성해링턴플레이스","a":75,"p":56500,"d":"2026-01-28","f":27},{"g":"용인시 기흥구","n":"금화마을4단지주공그린빌","a":84,"p":56500,"d":"2026-01-20","f":9},{"g":"용인시 기흥구","n":"SK","a":128,"p":56500,"d":"2026-01-22","f":7},{"g":"용인시 기흥구","n":"서천2차IPARK","a":75,"p":56500,"d":"2026-01-21","f":2},{"g":"용인시 기흥구","n":"신흥덕롯데캐슬레이시티","a":60,"p":56500,"d":"2026-01-10","f":2},{"g":"용인시 기흥구","n":"금화마을4단지주공그린빌","a":84,"p":56500,"d":"2026-01-09","f":8},{"g":"파주시","n":"파주운정신도시디에트르더클래스아파트","a":85,"p":56500,"d":"2026-01-17","f":9},{"g":"파주시","n":"한울마을1단지운정신도시IPARK","a":60,"p":56500,"d":"2026-01-16","f":7},{"g":"김포시","n":"풍무센트럴푸르지오","a":60,"p":56500,"d":"2026-01-24","f":14},{"g":"화성시 만세구","n":"송산신도시대방노블랜드리버스위트2차","a":85,"p":56500,"d":"2026-01-05","f":10},{"g":"화성시 동탄구","n":"능동마을이지더원","a":84,"p":56500,"d":"2026-01-26","f":15},{"g":"화성시 동탄구","n":"더레이크시티부영1단지","a":60,"p":56500,"d":"2026-01-25","f":7},{"g":"화성시 동탄구","n":"동탄역 신미주","a":85,"p":56500,"d":"2026-01-17","f":12},{"g":"화성시 동탄구","n":"더레이크시티부영1단지","a":60,"p":56500,"d":"2026-01-14","f":9},{"g":"화성시 동탄구","n":"푸르지오","a":58,"p":56500,"d":"2026-01-08","f":22},{"g":"광주시","n":"더샵오포센트리체","a":60,"p":56500,"d":"2026-01-07","f":9},{"g":"노원구","n":"태강아파트(아이파크)","a":50,"p":56400,"d":"2026-01-07","f":8},{"g":"구로구","n":"우성꿈동산","a":84,"p":56400,"d":"2026-01-24","f":9},{"g":"서구","n":"루원호반베르디움더센트럴","a":73,"p":56400,"d":"2026-01-21","f":4},{"g":"서구","n":"우미린더헤리티지","a":60,"p":56400,"d":"2026-01-02","f":20},{"g":"수원시 권선구","n":"벨섬시티","a":85,"p":56400,"d":"2026-01-10","f":14},{"g":"의정부시","n":"의정부역푸르지오더센트럴","a":60,"p":56400,"d":"2026-01-23","f":11},{"g":"화성시 동탄구","n":"동탄숲속마을자연앤경남아너스빌(1124-0)","a":77,"p":56350,"d":"2026-01-24","f":19},{"g":"구로구","n":"청구","a":60,"p":56300,"d":"2026-01-07","f":18},{"g":"수원시 장안구","n":"한일타운대림","a":85,"p":56300,"d":"2026-01-10","f":8},{"g":"수원시 장안구","n":"화서역 우방 센트럴파크","a":60,"p":56300,"d":"2026-01-05","f":4},{"g":"수원시 권선구","n":"쌍용더플래티넘오목천역","a":60,"p":56300,"d":"2026-01-10","f":6},{"g":"수원시 팔달구","n":"꽃뫼버들마을진흥","a":60,"p":56300,"d":"2026-01-29","f":4},{"g":"의정부시","n":"고산수자인디에스티지아트포레","a":80,"p":56300,"d":"2026-01-13","f":8},{"g":"부천시 원미구","n":"백송마을(풍림아이원)","a":60,"p":56300,"d":"2026-01-14","f":16},{"g":"부천시 오정구","n":"원종동금호어울림","a":60,"p":56300,"d":"2026-01-08","f":7},{"g":"안산시 단원구","n":"주공그린빌8","a":84,"p":56300,"d":"2026-01-25","f":9},{"g":"고양시 덕양구","n":"한라비발디","a":85,"p":56300,"d":"2026-01-26","f":13},{"g":"고양시 일산동구","n":"백마마을(금호)","a":84,"p":56300,"d":"2026-01-08","f":3},{"g":"고양시 일산동구","n":"백마마을(금호)","a":84,"p":56300,"d":"2026-01-13","f":5},{"g":"구리시","n":"우림","a":85,"p":56300,"d":"2026-01-21","f":10},{"g":"시흥시","n":"시흥시청역동원로얄듀크","a":74,"p":56300,"d":"2026-01-27","f":20},{"g":"군포시","n":"용호마을e-편한세상","a":85,"p":56300,"d":"2026-01-09","f":7},{"g":"고양시 덕양구","n":"은빛마을(삼성)5","a":100,"p":56250,"d":"2026-01-31","f":4},{"g":"군포시","n":"주공11","a":58,"p":56250,"d":"2026-01-23","f":5},{"g":"서구","n":"우미린더헤리티지","a":60,"p":56200,"d":"2026-01-10","f":26},{"g":"안양시 만안구","n":"한라비발디","a":85,"p":56200,"d":"2026-01-03","f":26},{"g":"수원시 팔달구","n":"화서주공5단지","a":50,"p":56150,"d":"2026-01-07","f":20},{"g":"용인시 기흥구","n":"용인보라효성해링턴플레이스","a":75,"p":56150,"d":"2026-01-31","f":11},{"g":"성남시 수정구","n":"밀란체2","a":85,"p":56100,"d":"2026-01-16","f":11},{"g":"중구","n":"정동","a":45,"p":56000,"d":"2026-01-30","f":4},{"g":"중랑구","n":"한국","a":60,"p":56000,"d":"2026-01-23","f":7},{"g":"노원구","n":"상계1차중앙하이츠","a":60,"p":56000,"d":"2026-01-23","f":12},{"g":"노원구","n":"주공8","a":50,"p":56000,"d":"2026-01-27","f":7},{"g":"노원구","n":"코오롱","a":60,"p":56000,"d":"2026-01-24","f":9},{"g":"노원구","n":"중계그린1단지","a":50,"p":56000,"d":"2026-01-16","f":3},{"g":"노원구","n":"보람아파트","a":69,"p":56000,"d":"2026-01-10","f":15},{"g":"은평구","n":"럭스빌(102동)","a":62,"p":56000,"d":"2026-01-18","f":7},{"g":"서대문구","n":"유원","a":85,"p":56000,"d":"2026-01-30","f":11},{"g":"양천구","n":"푸른마을2","a":49,"p":56000,"d":"2026-01-26","f":5},{"g":"구로구","n":"우성꿈동산","a":84,"p":56000,"d":"2026-01-14","f":2},{"g":"영등포구","n":"우성1","a":52,"p":56000,"d":"2026-01-28","f":11},{"g":"미추홀구","n":"포레나미추홀","a":77,"p":56000,"d":"2026-01-17","f":32},{"g":"미추홀구","n":"더샵인천스카이타워1단지","a":85,"p":56000,"d":"2026-01-08","f":18},{"g":"부평구","n":"중앙하이츠프리미어부평","a":85,"p":56000,"d":"2026-01-31","f":12},{"g":"부평구","n":"부평역화성파크드림","a":76,"p":56000,"d":"2026-01-31","f":28},{"g":"부평구","n":"e편한세상부평그랑힐스","a":60,"p":56000,"d":"2026-01-24","f":18},{"g":"부평구","n":"부평캐슬&더샵퍼스트","a":60,"p":56000,"d":"2026-01-29","f":20},{"g":"부평구","n":"힐스테이트부평","a":60,"p":56000,"d":"2026-01-14","f":9},{"g":"부평구","n":"부평캐슬&더샵퍼스트","a":60,"p":56000,"d":"2026-01-10","f":4},{"g":"부평구","n":"쌍용더플래티넘부평","a":72,"p":56000,"d":"2026-01-04","f":3},{"g":"계양구","n":"현대2-2차","a":149,"p":56000,"d":"2026-01-09","f":2},{"g":"서구","n":"검단신도시디에트르더펠리체","a":76,"p":56000,"d":"2026-01-30","f":19},{"g":"서구","n":"검암역로열파크씨티푸르지오1단지","a":74,"p":56000,"d":"2026-01-22","f":6},{"g":"서구","n":"가재울역트루엘에코시티","a":85,"p":56000,"d":"2026-01-25","f":7},{"g":"서구","n":"우미린더헤리티지","a":60,"p":56000,"d":"2026-01-22","f":13},{"g":"서구","n":"힐데스하임","a":60,"p":56000,"d":"2026-01-11","f":5},{"g":"서구","n":"검암역로열파크씨티푸르지오2단지","a":74,"p":56000,"d":"2026-01-01","f":3},{"g":"수원시 장안구","n":"한일타운태영","a":85,"p":56000,"d":"2026-01-21","f":16},{"g":"수원시 장안구","n":"성균관대역동문디이스트","a":60,"p":56000,"d":"2026-01-11","f":17},{"g":"수원시 장안구","n":"성균관대역동문디이스트","a":60,"p":56000,"d":"2026-01-10","f":15},{"g":"수원시 권선구","n":"권선3지구써미트빌","a":103,"p":56000,"d":"2026-01-27","f":5},{"g":"수원시 권선구","n":"수원시청역SKVIEW","a":85,"p":56000,"d":"2026-01-30","f":3},{"g":"수원시 권선구","n":"호매실역서희스타힐스","a":85,"p":56000,"d":"2026-01-31","f":8},{"g":"수원시 팔달구","n":"꽃뫼버들마을진흥","a":60,"p":56000,"d":"2026-01-09","f":9},{"g":"수원시 영통구","n":"e편한세상영통2차(1단지)","a":60,"p":56000,"d":"2026-01-26","f":22},{"g":"수원시 영통구","n":"신나무실동보","a":85,"p":56000,"d":"2026-01-03","f":3},{"g":"성남시 중원구","n":"은빛마을(두산위브)","a":57,"p":56000,"d":"2026-01-31","f":2},{"g":"성남시 중원구","n":"태연스카이빌","a":74,"p":56000,"d":"2026-01-03","f":4},{"g":"의정부시","n":"고산수자인디에스티지아트포레","a":80,"p":56000,"d":"2026-01-16","f":11},{"g":"안양시 만안구","n":"안양KCC스위첸","a":60,"p":56000,"d":"2026-01-17","f":11},{"g":"안양시 만안구","n":"코오롱하늘채","a":85,"p":56000,"d":"2026-01-11","f":2},{"g":"안양시 만안구","n":"현대아이파크","a":60,"p":56000,"d":"2026-01-20","f":10},{"g":"안양시 만안구","n":"성원1","a":85,"p":56000,"d":"2026-01-19","f":15},{"g":"안양시 만안구","n":"안양광신프로그레스리버뷰","a":51,"p":56000,"d":"2026-01-16","f":20},{"g":"안양시 만안구","n":"석수e-편한세상","a":60,"p":56000,"d":"2026-01-03","f":24},{"g":"안양시 동안구","n":"목련우성5","a":42,"p":56000,"d":"2026-01-29","f":4},{"g":"안양시 동안구","n":"삼성(931)","a":85,"p":56000,"d":"2026-01-23","f":9},{"g":"안양시 동안구","n":"목련우성5","a":42,"p":56000,"d":"2026-01-27","f":9},{"g":"부천시 원미구","n":"연화마을(쌍용)","a":85,"p":56000,"d":"2026-01-19","f":6},{"g":"부천시 원미구","n":"미리내마을(롯데2)","a":72,"p":56000,"d":"2026-01-15","f":6},{"g":"부천시 원미구","n":"미리내마을(동성)","a":78,"p":56000,"d":"2026-01-08","f":14},{"g":"부천시 소사구","n":"소사에스케이뷰","a":85,"p":56000,"d":"2026-01-29","f":4},{"g":"부천시 소사구","n":"부천범박힐스테이트4단지","a":100,"p":56000,"d":"2026-01-05","f":11},{"g":"광명시","n":"주공1","a":50,"p":56000,"d":"2026-01-10","f":9},{"g":"평택시","n":"힐스테이트지제역","a":85,"p":56000,"d":"2026-01-19","f":4},{"g":"평택시","n":"호반써밋고덕국제신도시에듀파크","a":85,"p":56000,"d":"2026-01-12","f":3},{"g":"안산시 상록구","n":"안산고잔7차푸르지오","a":89,"p":56000,"d":"2026-01-18","f":15},{"g":"안산시 상록구","n":"안산고잔9차푸르지오","a":102,"p":56000,"d":"2026-01-09","f":6},{"g":"안산시 상록구","n":"그랑시티자이","a":60,"p":56000,"d":"2026-01-06","f":37},{"g":"안산시 단원구","n":"대우푸르지오5","a":72,"p":56000,"d":"2026-01-15","f":10},{"g":"고양시 덕양구","n":"샘터마을(효성)","a":102,"p":56000,"d":"2026-01-16","f":8},{"g":"고양시 덕양구","n":"삼송10단지동일스위트2차","a":66,"p":56000,"d":"2026-01-27","f":8},{"g":"고양시 덕양구","n":"무원마을(동신)","a":102,"p":56000,"d":"2026-01-10","f":4},{"g":"고양시 덕양구","n":"별빛마을9단지(907동에서912동)","a":85,"p":56000,"d":"2026-01-03","f":19},{"g":"고양시 일산동구","n":"위시티일산자이2단지","a":130,"p":56000,"d":"2026-01-13","f":22},{"g":"고양시 일산서구","n":"일산두산위브더제니스","a":96,"p":56000,"d":"2026-01-08","f":39},{"g":"구리시","n":"원일아름","a":60,"p":56000,"d":"2026-01-23","f":15},{"g":"구리시","n":"수택동금호어울림","a":85,"p":56000,"d":"2026-01-29","f":4},{"g":"구리시","n":"교문(동양고속)","a":61,"p":56000,"d":"2026-01-18","f":1},{"g":"남양주시","n":"쌍용스윗닷홈리버","a":85,"p":56000,"d":"2026-01-26","f":5},{"g":"남양주시","n":"쌍용스윗닷홈리버","a":85,"p":56000,"d":"2026-01-09","f":15},{"g":"남양주시","n":"두산알프하임","a":85,"p":56000,"d":"2026-01-13","f":12},{"g":"오산시","n":"오산세교한신더휴","a":100,"p":56000,"d":"2026-01-30","f":25},{"g":"시흥시","n":"제일풍경채더숲","a":72,"p":56000,"d":"2026-01-17","f":22},{"g":"시흥시","n":"장현호반써밋","a":85,"p":56000,"d":"2026-01-12","f":4},{"g":"시흥시","n":"은계파크자이","a":60,"p":56000,"d":"2026-01-03","f":18},{"g":"군포시","n":"동백(우성)","a":102,"p":56000,"d":"2026-01-13","f":10},{"g":"군포시","n":"대림e-편한세상","a":85,"p":56000,"d":"2026-01-02","f":11},{"g":"의왕시","n":"대원칸타빌2","a":59,"p":56000,"d":"2026-01-09","f":3},{"g":"하남시","n":"부영","a":50,"p":56000,"d":"2026-01-24","f":1},{"g":"용인시 처인구","n":"서희스타힐스포레스트","a":84,"p":56000,"d":"2026-01-27","f":23},{"g":"용인시 처인구","n":"힐스테이트몬테로이1단지","a":85,"p":56000,"d":"2026-01-09","f":5},{"g":"용인시 기흥구","n":"하마비마을동부센트레빌","a":126,"p":56000,"d":"2026-01-29","f":8},{"g":"용인시 기흥구","n":"효성빌라(103동)","a":146,"p":56000,"d":"2026-01-26","f":4},{"g":"용인시 기흥구","n":"서천2차IPARK","a":75,"p":56000,"d":"2026-01-24","f":11},{"g":"용인시 기흥구","n":"교동마을마북이편한세상","a":85,"p":56000,"d":"2026-01-15","f":7},{"g":"용인시 기흥구","n":"초원마을성원상떼빌2차","a":130,"p":56000,"d":"2026-01-03","f":3},{"g":"용인시 기흥구","n":"한양수자인","a":89,"p":56000,"d":"2026-01-12","f":6},{"g":"용인시 기흥구","n":"대주피오레1단지","a":150,"p":56000,"d":"2026-01-09","f":12},{"g":"용인시 수지구","n":"삼익아파트","a":60,"p":56000,"d":"2026-01-14","f":5},{"g":"용인시 수지구","n":"수지신봉동도센트리움","a":60,"p":56000,"d":"2026-01-24","f":3},{"g":"용인시 수지구","n":"풍림아파트","a":60,"p":56000,"d":"2026-01-03","f":4},{"g":"파주시","n":"한울마을1단지운정신도시IPARK","a":60,"p":56000,"d":"2026-01-31","f":13},{"g":"파주시","n":"초롱꽃마을12단지e편한세상운정어반프라임","a":75,"p":56000,"d":"2026-01-19","f":4},{"g":"김포시","n":"풍무푸르지오센트레빌","a":60,"p":56000,"d":"2026-01-24","f":17},{"g":"김포시","n":"양도마을(서해그랑블)","a":197,"p":56000,"d":"2026-01-17","f":3},{"g":"김포시","n":"한강메트로자이1단지","a":74,"p":56000,"d":"2026-01-03","f":25},{"g":"화성시 만세구","n":"송산신도시대방노블랜드더퍼스티지1차","a":85,"p":56000,"d":"2026-01-29","f":7},{"g":"화성시 만세구","n":"금강펜테리움센트럴파크송산","a":84,"p":56000,"d":"2026-01-27","f":9},{"g":"화성시 만세구","n":"금강펜테리움센트럴파크송산","a":84,"p":56000,"d":"2026-01-02","f":19},{"g":"화성시 효행구","n":"봉담자이라피네","a":85,"p":56000,"d":"2026-01-03","f":17},{"g":"화성시 병점구","n":"에스케이뷰파크","a":115,"p":56000,"d":"2026-01-27","f":8},{"g":"화성시 동탄구","n":"동탄숲속마을자연앤경남아너스빌(1115-0)","a":77,"p":56000,"d":"2026-01-28","f":5},{"g":"화성시 동탄구","n":"서희스타힐스엔에이치에프","a":75,"p":56000,"d":"2026-01-17","f":10},{"g":"화성시 동탄구","n":"더레이크시티부영1단지","a":60,"p":56000,"d":"2026-01-19","f":6},{"g":"화성시 동탄구","n":"동탄2신도시호반베르디움22단지","a":54,"p":56000,"d":"2026-01-09","f":9},{"g":"광주시","n":"이편한세상광주역3단지","a":60,"p":56000,"d":"2026-01-25","f":1},{"g":"광주시","n":"광주역우방아이유쉘2단지","a":85,"p":56000,"d":"2026-01-24","f":8},{"g":"노원구","n":"상계주공11(고층)","a":59,"p":55900,"d":"2026-01-24","f":2},{"g":"구로구","n":"동부골든","a":85,"p":55900,"d":"2026-01-29","f":18},{"g":"의정부시","n":"의정부역푸르지오더센트럴","a":60,"p":55900,"d":"2026-01-09","f":6},{"g":"구리시","n":"교문(대우)","a":61,"p":55900,"d":"2026-01-18","f":1},{"g":"구로구","n":"우성,현대아파트","a":58,"p":55800,"d":"2026-01-05","f":4},{"g":"미추홀구","n":"인천 SK Sky VIEW","a":85,"p":55800,"d":"2026-01-14","f":31},{"g":"연수구","n":"송도풍림아이원2단지","a":85,"p":55800,"d":"2026-01-20","f":5},{"g":"부평구","n":"삼산타운2단지","a":85,"p":55800,"d":"2026-01-24","f":21},{"g":"수원시 팔달구","n":"우만주공2단지","a":58,"p":55800,"d":"2026-01-14","f":5},{"g":"안양시 만안구","n":"한라비발디","a":85,"p":55800,"d":"2026-01-26","f":23},{"g":"부천시 원미구","n":"백송마을(풍림아이원)","a":60,"p":55800,"d":"2026-01-21","f":13},{"g":"구리시","n":"한진","a":85,"p":55800,"d":"2026-01-10","f":8},{"g":"구리시","n":"주공4-2","a":60,"p":55800,"d":"2026-01-24","f":2},{"g":"시흥시","n":"목감퍼스트리움","a":60,"p":55800,"d":"2026-01-31","f":17},{"g":"군포시","n":"주공11","a":58,"p":55800,"d":"2026-01-24","f":10},{"g":"용인시 기흥구","n":"신흥덕롯데캐슬레이시티","a":60,"p":55800,"d":"2026-01-31","f":18},{"g":"김포시","n":"힐스테이트 리버시티 2단지","a":77,"p":55800,"d":"2026-01-17","f":8},{"g":"화성시 만세구","n":"금강펜테리움센트럴파크송산","a":84,"p":55800,"d":"2026-01-26","f":14},{"g":"화성시 동탄구","n":"푸르지오","a":58,"p":55800,"d":"2026-01-23","f":9},{"g":"화성시 동탄구","n":"동탄역포레너스","a":60,"p":55800,"d":"2026-01-10","f":10},{"g":"광주시","n":"더샵오포센트럴포레","a":77,"p":55800,"d":"2026-01-17","f":3},{"g":"용인시 기흥구","n":"동원마을동원로얄듀크","a":120,"p":55750,"d":"2026-01-27","f":4},{"g":"양천구","n":"학마을1단지","a":50,"p":55700,"d":"2026-01-09","f":2},{"g":"수원시 장안구","n":"성균관대역동문디이스트","a":60,"p":55700,"d":"2026-01-10","f":8},{"g":"수원시 권선구","n":"벨섬시티","a":85,"p":55700,"d":"2026-01-19","f":11},{"g":"수원시 영통구","n":"벽적골9단지주공","a":59,"p":55700,"d":"2026-01-07","f":18},{"g":"고양시 일산서구","n":"일산두산위브더제니스","a":96,"p":55700,"d":"2026-01-28","f":4},{"g":"구리시","n":"동방","a":60,"p":55700,"d":"2026-01-30","f":6},{"g":"구리시","n":"쌍용","a":60,"p":55700,"d":"2026-01-16","f":3},{"g":"구리시","n":"쌍용","a":60,"p":55700,"d":"2026-01-08","f":10},{"g":"구리시","n":"교문(동양고속)","a":61,"p":55700,"d":"2026-01-06","f":1},{"g":"군포시","n":"한양백두","a":151,"p":55700,"d":"2026-01-10","f":1},{"g":"의왕시","n":"대원칸타빌1","a":60,"p":55700,"d":"2026-01-24","f":10},{"g":"용인시 기흥구","n":"녹원마을새천년그린빌(1)","a":60,"p":55700,"d":"2026-01-16","f":3},{"g":"용인시 기흥구","n":"금화마을4단지주공그린빌","a":84,"p":55700,"d":"2026-01-16","f":3},{"g":"화성시 동탄구","n":"동탄2신도시금강펜테리움센트럴파크Ⅰ","a":70,"p":55700,"d":"2026-01-10","f":10},{"g":"의정부시","n":"호반베르디움1차","a":85,"p":55600,"d":"2026-01-26","f":22},{"g":"의정부시","n":"의정부역푸르지오더센트럴","a":60,"p":55600,"d":"2026-01-10","f":24},{"g":"시흥시","n":"시흥은계한양수자인더클래스","a":76,"p":55600,"d":"2026-01-19","f":11},{"g":"시흥시","n":"은계어반리더스","a":85,"p":55600,"d":"2026-01-12","f":4},{"g":"중랑구","n":"신안2","a":60,"p":55500,"d":"2026-01-29","f":8},{"g":"중랑구","n":"신내","a":60,"p":55500,"d":"2026-01-19","f":8},{"g":"구로구","n":"삼천리","a":60,"p":55500,"d":"2026-01-24","f":25},{"g":"구로구","n":"구일우성","a":59,"p":55500,"d":"2026-01-28","f":18},{"g":"금천구","n":"관악산벽산타운5","a":85,"p":55500,"d":"2026-01-10","f":18},{"g":"미추홀구","n":"힐스테이트학익","a":74,"p":55500,"d":"2026-01-24","f":27},{"g":"연수구","n":"e편한세상송도","a":70,"p":55500,"d":"2026-01-03","f":18},{"g":"서구","n":"검단신도시대성베르힐라프리미어","a":85,"p":55500,"d":"2026-01-09","f":8},{"g":"서구","n":"힐데스하임","a":60,"p":55500,"d":"2026-01-06","f":20},{"g":"수원시 권선구","n":"호매실역서희스타힐스","a":85,"p":55500,"d":"2026-01-14","f":5},{"g":"수원시 권선구","n":"쌍용더플래티넘오목천역","a":60,"p":55500,"d":"2026-01-25","f":9},{"g":"수원시 권선구","n":"쌍용더플래티넘오목천역","a":60,"p":55500,"d":"2026-01-08","f":6},{"g":"수원시 팔달구","n":"우만주공2단지","a":58,"p":55500,"d":"2026-01-14","f":14},{"g":"성남시 수정구","n":"세일띠아모아파트","a":55,"p":55500,"d":"2026-01-19","f":13},{"g":"의정부시","n":"호반베르디움1차","a":85,"p":55500,"d":"2026-01-24","f":7},{"g":"안양시 만안구","n":"한라비발디","a":85,"p":55500,"d":"2026-01-24","f":15},{"g":"안양시 동안구","n":"대주파크빌","a":83,"p":55500,"d":"2026-01-09","f":2},{"g":"부천시 원미구","n":"미리내마을(롯데2)","a":64,"p":55500,"d":"2026-01-15","f":5},{"g":"부천시 원미구","n":"한아름마을(삼환,동아,동성)","a":85,"p":55500,"d":"2026-01-29","f":14},{"g":"부천시 원미구","n":"꿈마을(삼환)","a":81,"p":55500,"d":"2026-01-14","f":1},{"g":"안산시 단원구","n":"안산푸르지오브리파크","a":60,"p":55500,"d":"2026-01-19","f":14},{"g":"구리시","n":"수택주공","a":60,"p":55500,"d":"2026-01-31","f":17},{"g":"구리시","n":"토평주공","a":60,"p":55500,"d":"2026-01-17","f":10},{"g":"구리시","n":"우방아이유쉘","a":85,"p":55500,"d":"2026-01-26","f":12},{"g":"구리시","n":"구리인창금호어울림","a":85,"p":55500,"d":"2026-01-05","f":10},{"g":"구리시","n":"한진","a":85,"p":55500,"d":"2026-01-01","f":16},{"g":"시흥시","n":"시흥은계우미린레이크","a":85,"p":55500,"d":"2026-01-24","f":4},{"g":"시흥시","n":"목감퍼스트리움","a":60,"p":55500,"d":"2026-01-26","f":11},{"g":"시흥시","n":"시흥능곡역모아미래도에듀포레","a":85,"p":55500,"d":"2026-01-26","f":12},{"g":"시흥시","n":"시흥능곡역모아미래도에듀포레","a":85,"p":55500,"d":"2026-01-21","f":21},{"g":"의왕시","n":"한진해모로","a":85,"p":55500,"d":"2026-01-02","f":14},{"g":"용인시 기흥구","n":"신흥덕롯데캐슬레이시티","a":60,"p":55500,"d":"2026-01-10","f":3},{"g":"용인시 기흥구","n":"용인기흥효성해링턴플레이스","a":74,"p":55500,"d":"2026-01-27","f":17},{"g":"용인시 기흥구","n":"용인기흥효성해링턴플레이스","a":74,"p":55500,"d":"2026-01-14","f":26},{"g":"용인시 기흥구","n":"한양수자인","a":89,"p":55500,"d":"2026-01-01","f":5},{"g":"파주시","n":"산내마을7단지화성파크드림","a":85,"p":55500,"d":"2026-01-20","f":12},{"g":"김포시","n":"e편한세상캐널시티","a":84,"p":55500,"d":"2026-01-31","f":24},{"g":"김포시","n":"한강메트로자이2단지","a":60,"p":55500,"d":"2026-01-19","f":30},{"g":"화성시 만세구","n":"금강펜테리움센트럴파크송산","a":84,"p":55500,"d":"2026-01-24","f":7},{"g":"화성시 동탄구","n":"동탄역포레너스","a":60,"p":55500,"d":"2026-01-13","f":5},{"g":"화성시 동탄구","n":"자연앤데시앙","a":85,"p":55500,"d":"2026-01-16","f":1},{"g":"화성시 동탄구","n":"동탄2하우스디더레이크","a":60,"p":55500,"d":"2026-01-15","f":1},{"g":"광주시","n":"광주센트럴푸르지오","a":85,"p":55500,"d":"2026-01-24","f":17},{"g":"광주시","n":"힐스테이트태전2차에듀포레C10BL","a":73,"p":55500,"d":"2026-01-25","f":19},{"g":"광주시","n":"더샵오포센트리체","a":60,"p":55500,"d":"2026-01-30","f":3},{"g":"광주시","n":"힐스테이트태전(C5,1507~1514동)","a":73,"p":55500,"d":"2026-01-10","f":18},{"g":"양평군","n":"더샵양평리버포레","a":85,"p":55500,"d":"2026-01-08","f":3},{"g":"노원구","n":"상계주공14(고층)","a":59,"p":55400,"d":"2026-01-30","f":4},{"g":"남동구","n":"인천시청역힐스테이트","a":60,"p":55400,"d":"2026-01-31","f":24},{"g":"서구","n":"검단신도시대성베르힐라프리미어","a":85,"p":55400,"d":"2026-01-17","f":23},{"g":"성남시 중원구","n":"은빛마을(두산위브)","a":57,"p":55400,"d":"2026-01-07","f":4},{"g":"구리시","n":"구리갈매푸르지오","a":84,"p":55400,"d":"2026-01-23","f":25},{"g":"화성시 효행구","n":"중흥에스클래스에듀파크","a":84,"p":55400,"d":"2026-01-11","f":1},{"g":"화성시 동탄구","n":"힐스테이트동탄역","a":55,"p":55400,"d":"2026-01-08","f":34},{"g":"강북구","n":"주공1단지","a":50,"p":55300,"d":"2026-01-31","f":14},{"g":"강북구","n":"번동금호어울림","a":85,"p":55300,"d":"2026-01-14","f":5},{"g":"노원구","n":"태강아파트(아이파크)","a":50,"p":55300,"d":"2026-01-17","f":11},{"g":"남동구","n":"간석래미안자이","a":85,"p":55300,"d":"2026-01-06","f":14},{"g":"수원시 팔달구","n":"화서주공5단지","a":50,"p":55300,"d":"2026-01-09","f":6},{"g":"의정부시","n":"호반베르디움1차","a":85,"p":55300,"d":"2026-01-26","f":5},{"g":"부천시 소사구","n":"소사에스케이뷰","a":85,"p":55300,"d":"2026-01-10","f":7},{"g":"구리시","n":"우방아이유쉘","a":85,"p":55300,"d":"2026-01-31","f":4},{"g":"용인시 처인구","n":"골드클래스","a":84,"p":55300,"d":"2026-01-09","f":18},{"g":"파주시","n":"초롱꽃마을12단지e편한세상운정어반프라임","a":85,"p":55300,"d":"2026-01-20","f":1},{"g":"화성시 효행구","n":"중흥에스클래스더센트럴","a":73,"p":55300,"d":"2026-01-14","f":11},{"g":"화성시 동탄구","n":"동탄역이지더원","a":60,"p":55300,"d":"2026-01-22","f":1},{"g":"화성시 동탄구","n":"동탄숲속마을자연앤경남아너스빌(1124-0)","a":77,"p":55300,"d":"2026-01-02","f":12},{"g":"화성시 병점구","n":"e편한세상반월나노시티역","a":58,"p":55250,"d":"2026-01-30","f":3},{"g":"수원시 영통구","n":"풍림","a":85,"p":55200,"d":"2026-01-20","f":16},{"g":"의정부시","n":"의정부역푸르지오더센트럴","a":60,"p":55200,"d":"2026-01-06","f":4},{"g":"안산시 단원구","n":"양지마을","a":85,"p":55200,"d":"2026-01-05","f":4},{"g":"광주시","n":"이편한세상광주역1단지","a":60,"p":55200,"d":"2026-01-21","f":8},{"g":"광주시","n":"힐스테이트태전2차에듀포레C10BL","a":73,"p":55200,"d":"2026-01-05","f":22},{"g":"김포시","n":"힐스테이트 리버시티 2단지","a":77,"p":55100,"d":"2026-01-14","f":21},{"g":"동대문구","n":"시온","a":63,"p":55000,"d":"2026-01-22","f":4},{"g":"중랑구","n":"신내6대주","a":50,"p":55000,"d":"2026-01-18","f":6},{"g":"성북구","n":"우방","a":85,"p":55000,"d":"2026-01-19","f":3},{"g":"강북구","n":"주공1단지","a":50,"p":55000,"d":"2026-01-17","f":11},{"g":"강북구","n":"주공1단지","a":50,"p":55000,"d":"2026-01-20","f":1},{"g":"노원구","n":"상계주공1(고층)","a":50,"p":55000,"d":"2026-01-30","f":10},{"g":"노원구","n":"상계주공12(고층)","a":50,"p":55000,"d":"2026-01-28","f":4},{"g":"노원구","n":"대동","a":60,"p":55000,"d":"2026-01-23","f":4},{"g":"노원구","n":"동신아파트","a":85,"p":55000,"d":"2026-01-26","f":16},{"g":"노원구","n":"상계1차현대아파트","a":84,"p":55000,"d":"2026-01-21","f":3},{"g":"은평구","n":"이랜드타운아파트","a":60,"p":55000,"d":"2026-01-10","f":23},{"g":"은평구","n":"대주파크빌","a":60,"p":55000,"d":"2026-01-15","f":8},{"g":"은평구","n":"미성","a":64,"p":55000,"d":"2026-01-15","f":8},{"g":"양천구","n":"건영","a":84,"p":55000,"d":"2026-01-30","f":11},{"g":"강서구","n":"마곡서광(치현마을)","a":85,"p":55000,"d":"2026-01-14","f":14},{"g":"강서구","n":"일성스카이빌","a":114,"p":55000,"d":"2026-01-10","f":14},{"g":"강서구","n":"장미","a":49,"p":55000,"d":"2026-01-12","f":12},{"g":"구로구","n":"덕영드림","a":56,"p":55000,"d":"2026-01-17","f":13},{"g":"구로구","n":"구일우성","a":59,"p":55000,"d":"2026-01-06","f":12},{"g":"구로구","n":"두산","a":60,"p":55000,"d":"2026-01-05","f":25},{"g":"구로구","n":"삼환","a":59,"p":55000,"d":"2026-01-03","f":4},{"g":"금천구","n":"관악산벽산타운5","a":85,"p":55000,"d":"2026-01-17","f":3},{"g":"금천구","n":"남서울건영아파트","a":77,"p":55000,"d":"2026-01-05","f":3},{"g":"관악구","n":"삼원하이츠11차","a":75,"p":55000,"d":"2026-01-26","f":3},{"g":"관악구","n":"LIG대학마을(건영아파트3차)","a":59,"p":55000,"d":"2026-01-10","f":10},{"g":"관악구","n":"건영1","a":60,"p":55000,"d":"2026-01-19","f":12},{"g":"서초구","n":"대림서초리시온","a":46,"p":55000,"d":"2026-01-24","f":9},{"g":"강동구","n":"우성101동","a":85,"p":55000,"d":"2026-01-15","f":1},{"g":"강동구","n":"우정에쉐르(101동)","a":60,"p":55000,"d":"2026-01-09","f":3},{"g":"중구","n":"스카이시티자이","a":99,"p":55000,"d":"2026-01-03","f":13},{"g":"미추홀구","n":"인천 SK Sky VIEW","a":85,"p":55000,"d":"2026-01-10","f":16},{"g":"남동구","n":"호반베르디움","a":85,"p":55000,"d":"2026-01-20","f":19},{"g":"남동구","n":"에코메트로6","a":85,"p":55000,"d":"2026-01-31","f":20},{"g":"남동구","n":"인천시청역힐스테이트","a":60,"p":55000,"d":"2026-01-29","f":19},{"g":"남동구","n":"롯데캐슬골드","a":85,"p":55000,"d":"2026-01-22","f":22},{"g":"남동구","n":"구월유승한내들퍼스티지","a":84,"p":55000,"d":"2026-01-16","f":21},{"g":"남동구","n":"에코메트로7","a":85,"p":55000,"d":"2026-01-12","f":21},{"g":"부평구","n":"부평신일해피트리더루츠","a":60,"p":55000,"d":"2026-01-31","f":16},{"g":"서구","n":"검단신도시대방디에트르리버파크","a":60,"p":55000,"d":"2026-01-21","f":14},{"g":"서구","n":"검단신도시대방디에트르리버파크","a":60,"p":55000,"d":"2026-01-26","f":16},{"g":"서구","n":"호반써밋프라임뷰","a":73,"p":55000,"d":"2026-01-14","f":15},{"g":"서구","n":"검단신도시모아엘가그랑데","a":60,"p":55000,"d":"2026-01-06","f":9},{"g":"수원시 장안구","n":"꽃뫼마을신안","a":85,"p":55000,"d":"2026-01-23","f":10},{"g":"수원시 장안구","n":"한일타운쌍용","a":85,"p":55000,"d":"2026-01-13","f":6},{"g":"수원시 장안구","n":"두견마을벽산3차","a":100,"p":55000,"d":"2026-01-12","f":8},{"g":"수원시 장안구","n":"한일타운태영","a":85,"p":55000,"d":"2026-01-02","f":17},{"g":"수원시 권선구","n":"수원역센트럴타운","a":60,"p":55000,"d":"2026-01-28","f":10},{"g":"수원시 권선구","n":"수원하늘채더퍼스트1단지","a":60,"p":55000,"d":"2026-01-31","f":13},{"g":"수원시 팔달구","n":"화서주공4단지","a":50,"p":55000,"d":"2026-01-29","f":16},{"g":"수원시 팔달구","n":"우만주공2단지","a":59,"p":55000,"d":"2026-01-22","f":7},{"g":"수원시 팔달구","n":"꽃뫼버들마을진흥","a":60,"p":55000,"d":"2026-01-19","f":14},{"g":"수원시 팔달구","n":"우만주공2단지","a":58,"p":55000,"d":"2026-01-10","f":9},{"g":"성남시 수정구","n":"미래타운2차","a":62,"p":55000,"d":"2026-01-31","f":12},{"g":"의정부시","n":"의정부역센트럴자이앤위브캐슬","a":60,"p":55000,"d":"2026-01-30","f":10},{"g":"의정부시","n":"호반베르디움1차","a":85,"p":55000,"d":"2026-01-13","f":16},{"g":"의정부시","n":"호반베르디움1차","a":85,"p":55000,"d":"2026-01-19","f":13},{"g":"안양시 만안구","n":"한라비발디","a":85,"p":55000,"d":"2026-01-24","f":13},{"g":"안양시 만안구","n":"두산위브더아티움","a":47,"p":55000,"d":"2026-01-14","f":19},{"g":"안양시 만안구","n":"현대아이파크","a":85,"p":55000,"d":"2026-01-31","f":1}]}