{
  "ticker": "038060",
  "name": "루멘스",
  "quarterly": [
    {
      "period": "2025Q4",
      "stac_yymm": "202512",
      "revenue": 465,
      "operating_profit": -22,
      "net_income": -22,
      "op_margin": -4.731182795698925,
      "yoy_revenue": 2.4229074889867843,
      "yoy_op": -152.38095238095238,
      "qoq_revenue": 4.72972972972973,
      "qoq_op": -2100
    },
    {
      "period": "2025Q3",
      "stac_yymm": "202509",
      "revenue": 444,
      "operating_profit": -1,
      "net_income": -1,
      "op_margin": -0.22522522522522523,
      "yoy_revenue": -7.306889352818372,
      "yoy_op": -133.33333333333331,
      "qoq_revenue": 20.98092643051771,
      "qoq_op": 98.0392156862745
    },
    {
      "period": "2025Q2",
      "stac_yymm": "202506",
      "revenue": 367,
      "operating_profit": -51,
      "net_income": -51,
      "op_margin": -13.896457765667575,
      "yoy_revenue": -11.990407673860911,
      "yoy_op": -304,
      "qoq_revenue": -23.382045929018787,
      "qoq_op": -828.5714285714287
    },
    {
      "period": "2025Q1",
      "stac_yymm": "202503",
      "revenue": 479,
      "operating_profit": 7,
      "net_income": 7,
      "op_margin": 1.4613778705636742,
      "yoy_revenue": 22.193877551020407,
      "yoy_op": -78.78787878787878,
      "qoq_revenue": 5.506607929515418,
      "qoq_op": -83.33333333333334
    },
    {
      "period": "2024Q4",
      "stac_yymm": "202412",
      "revenue": 454,
      "operating_profit": 42,
      "net_income": 38,
      "op_margin": 9.251101321585903,
      "yoy_revenue": 15.228426395939088,
      "yoy_op": 362.5,
      "qoq_revenue": -5.219206680584551,
      "qoq_op": 1300
    },
    {
      "period": "2024Q3",
      "stac_yymm": "202409",
      "revenue": 479,
      "operating_profit": 3,
      "net_income": 5,
      "op_margin": 0.6263048016701461,
      "yoy_revenue": 1.0548523206751055,
      "yoy_op": -86.95652173913044,
      "qoq_revenue": 14.86810551558753,
      "qoq_op": -88
    },
    {
      "period": "2024Q2",
      "stac_yymm": "202406",
      "revenue": 417,
      "operating_profit": 25,
      "net_income": 13,
      "op_margin": 5.995203836930456,
      "yoy_revenue": 2.70935960591133,
      "yoy_op": 257.14285714285717,
      "qoq_revenue": 6.377551020408164,
      "qoq_op": -24.242424242424242
    },
    {
      "period": "2024Q1",
      "stac_yymm": "202403",
      "revenue": 392,
      "operating_profit": 33,
      "net_income": 32,
      "op_margin": 8.418367346938775,
      "yoy_revenue": -10.50228310502283,
      "yoy_op": -10.81081081081081,
      "qoq_revenue": -0.5076142131979695,
      "qoq_op": 306.25
    },
    {
      "period": "2023Q4",
      "stac_yymm": "202312",
      "revenue": 394,
      "operating_profit": -16,
      "net_income": -23,
      "op_margin": -4.060913705583756,
      "yoy_revenue": -5.741626794258373,
      "yoy_op": 81.81818181818183,
      "qoq_revenue": -16.877637130801688,
      "qoq_op": -169.56521739130434
    },
    {
      "period": "2023Q3",
      "stac_yymm": "202309",
      "revenue": 474,
      "operating_profit": 23,
      "net_income": 20,
      "op_margin": 4.852320675105485,
      "yoy_revenue": 20,
      "yoy_op": -43.90243902439025,
      "qoq_revenue": 16.748768472906402,
      "qoq_op": 228.57142857142856
    },
    {
      "period": "2023Q2",
      "stac_yymm": "202306",
      "revenue": 406,
      "operating_profit": 7,
      "net_income": 6,
      "op_margin": 1.7241379310344827,
      "yoy_revenue": 15.01416430594901,
      "yoy_op": -66.66666666666666,
      "qoq_revenue": -7.30593607305936,
      "qoq_op": -81.08108108108108
    },
    {
      "period": "2023Q1",
      "stac_yymm": "202303",
      "revenue": 438,
      "operating_profit": 37,
      "net_income": 37,
      "op_margin": 8.447488584474886,
      "yoy_revenue": -11.87122736418511,
      "yoy_op": -80.52631578947368,
      "qoq_revenue": 4.784688995215311,
      "qoq_op": 142.04545454545453
    },
    {
      "period": "2022Q4",
      "stac_yymm": "202212",
      "revenue": 418,
      "operating_profit": -88,
      "net_income": -82,
      "op_margin": -21.052631578947366,
      "yoy_revenue": 44.636678200692046,
      "yoy_op": 55.778894472361806,
      "qoq_revenue": 5.822784810126582,
      "qoq_op": -314.6341463414634
    },
    {
      "period": "2022Q3",
      "stac_yymm": "202209",
      "revenue": 395,
      "operating_profit": 41,
      "net_income": 31,
      "op_margin": 10.379746835443038,
      "yoy_revenue": -30.579964850615116,
      "yoy_op": 78.26086956521739,
      "qoq_revenue": 11.89801699716714,
      "qoq_op": 95.23809523809523
    },
    {
      "period": "2022Q2",
      "stac_yymm": "202206",
      "revenue": 353,
      "operating_profit": 21,
      "net_income": 24,
      "op_margin": 5.94900849858357,
      "yoy_revenue": 64.95327102803739,
      "yoy_op": 223.52941176470588,
      "qoq_revenue": -28.973843058350102,
      "qoq_op": -88.94736842105263
    },
    {
      "period": "2022Q1",
      "stac_yymm": "202203",
      "revenue": 497,
      "operating_profit": 190,
      "net_income": 186,
      "op_margin": 38.22937625754527,
      "yoy_revenue": -23.655913978494624,
      "yoy_op": 691.6666666666667,
      "qoq_revenue": 71.97231833910035,
      "qoq_op": 195.47738693467335
    },
    {
      "period": "2021Q4",
      "stac_yymm": "202112",
      "revenue": 289,
      "operating_profit": -199,
      "net_income": -202,
      "op_margin": -68.85813148788927,
      "yoy_revenue": -22.311827956989248,
      "yoy_op": -121.1111111111111,
      "qoq_revenue": -49.209138840070295,
      "qoq_op": -965.2173913043479
    },
    {
      "period": "2021Q3",
      "stac_yymm": "202109",
      "revenue": 569,
      "operating_profit": 23,
      "net_income": 24,
      "op_margin": 4.042179261862917,
      "yoy_revenue": -24.43559096945551,
      "yoy_op": -39.473684210526315,
      "qoq_revenue": 165.88785046728972,
      "qoq_op": 235.29411764705884
    },
    {
      "period": "2021Q2",
      "stac_yymm": "202106",
      "revenue": 214,
      "operating_profit": -17,
      "net_income": -141,
      "op_margin": -7.943925233644859,
      "yoy_revenue": 5.9405940594059405,
      "yoy_op": -183.33333333333331,
      "qoq_revenue": -67.12749615975423,
      "qoq_op": -170.83333333333331
    },
    {
      "period": "2021Q1",
      "stac_yymm": "202103",
      "revenue": 651,
      "operating_profit": 24,
      "net_income": 25,
      "op_margin": 3.686635944700461,
      "yoy_revenue": -10.330578512396695,
      "yoy_op": -52,
      "qoq_revenue": 75,
      "qoq_op": 126.66666666666666
    },
    {
      "period": "2020Q4",
      "stac_yymm": "202012",
      "revenue": 372,
      "operating_profit": -90,
      "net_income": -348,
      "op_margin": -24.193548387096776,
      "yoy_revenue": -50.79365079365079,
      "yoy_op": 82.21343873517787,
      "qoq_revenue": -50.59760956175299,
      "qoq_op": -336.84210526315786
    },
    {
      "period": "2020Q3",
      "stac_yymm": "202009",
      "revenue": 753,
      "operating_profit": 38,
      "net_income": 34,
      "op_margin": 5.046480743691899,
      "yoy_revenue": -20.736842105263158,
      "yoy_op": 65.21739130434783,
      "qoq_revenue": 272.7722772277228,
      "qoq_op": 733.3333333333333
    },
    {
      "period": "2020Q2",
      "stac_yymm": "202006",
      "revenue": 202,
      "operating_profit": -6,
      "net_income": -13,
      "op_margin": -2.9702970297029703,
      "yoy_revenue": -76.9406392694064,
      "yoy_op": -250,
      "qoq_revenue": -72.1763085399449,
      "qoq_op": -112.00000000000001
    },
    {
      "period": "2020Q1",
      "stac_yymm": "202003",
      "revenue": 726,
      "operating_profit": 50,
      "net_income": 44,
      "op_margin": 6.887052341597796,
      "yoy_revenue": 11.009174311926607,
      "yoy_op": 206.38297872340425,
      "qoq_revenue": -3.968253968253968,
      "qoq_op": 109.8814229249012
    },
    {
      "period": "2019Q4",
      "stac_yymm": "201912",
      "revenue": 756,
      "operating_profit": -506,
      "net_income": -589,
      "op_margin": -66.93121693121694,
      "yoy_revenue": -36.36363636363637,
      "yoy_op": -391.2621359223301,
      "qoq_revenue": -20.42105263157895,
      "qoq_op": -2300
    },
    {
      "period": "2019Q3",
      "stac_yymm": "201909",
      "revenue": 950,
      "operating_profit": 23,
      "net_income": 22,
      "op_margin": 2.4210526315789473,
      "yoy_revenue": -54.106280193236714,
      "yoy_op": 114.64968152866241,
      "qoq_revenue": 8.447488584474886,
      "qoq_op": 475
    },
    {
      "period": "2019Q2",
      "stac_yymm": "201906",
      "revenue": 876,
      "operating_profit": 4,
      "net_income": 1,
      "op_margin": 0.45662100456621,
      "yoy_revenue": null,
      "yoy_op": null,
      "qoq_revenue": 33.94495412844037,
      "qoq_op": 108.51063829787233
    },
    {
      "period": "2019Q1",
      "stac_yymm": "201903",
      "revenue": 654,
      "operating_profit": -47,
      "net_income": -45,
      "op_margin": -7.186544342507645,
      "yoy_revenue": null,
      "yoy_op": null,
      "qoq_revenue": -44.94949494949495,
      "qoq_op": 54.36893203883495
    },
    {
      "period": "2018Q4",
      "stac_yymm": "201812",
      "revenue": 1188,
      "operating_profit": -103,
      "net_income": -178,
      "op_margin": -8.67003367003367,
      "yoy_revenue": null,
      "yoy_op": null,
      "qoq_revenue": -42.608695652173914,
      "qoq_op": 34.394904458598724
    },
    {
      "period": "2018Q3",
      "stac_yymm": "201809",
      "revenue": 2070,
      "operating_profit": -157,
      "net_income": -137,
      "op_margin": -7.584541062801932,
      "yoy_revenue": null,
      "yoy_op": null,
      "qoq_revenue": null,
      "qoq_op": null
    }
  ],
  "annual": [
    {
      "year": "2025",
      "revenue": 1755,
      "operating_profit": -67,
      "net_income": -67,
      "op_margin": -3.8176638176638176
    },
    {
      "year": "2024",
      "revenue": 1742,
      "operating_profit": 103,
      "net_income": 88,
      "op_margin": 5.912743972445465
    },
    {
      "year": "2023",
      "revenue": 1712,
      "operating_profit": 51,
      "net_income": 40,
      "op_margin": 2.9789719626168223
    },
    {
      "year": "2022",
      "revenue": 1663,
      "operating_profit": 164,
      "net_income": 159,
      "op_margin": 9.861695730607337
    },
    {
      "year": "2021",
      "revenue": 1723,
      "operating_profit": -169,
      "net_income": -294,
      "op_margin": -9.808473592571097
    },
    {
      "year": "2020",
      "revenue": 2053,
      "operating_profit": -8,
      "net_income": -283,
      "op_margin": -0.3896736483195324
    },
    {
      "year": "2019",
      "revenue": 3236,
      "operating_profit": -526,
      "net_income": -611,
      "op_margin": -16.254635352286773
    },
    {
      "year": "2018",
      "revenue": 3258,
      "operating_profit": -260,
      "net_income": -315,
      "op_margin": -7.980356046654389
    },
    {
      "year": "2017",
      "revenue": 3616,
      "operating_profit": -98,
      "net_income": 12,
      "op_margin": -2.7101769911504423
    },
    {
      "year": "2016",
      "revenue": 4028,
      "operating_profit": -58,
      "net_income": -62,
      "op_margin": -1.4399205561072492
    },
    {
      "year": "2015",
      "revenue": 4256,
      "operating_profit": -61,
      "net_income": -79,
      "op_margin": -1.4332706766917291
    },
    {
      "year": "2014",
      "revenue": 5245,
      "operating_profit": 160,
      "net_income": 117,
      "op_margin": 3.0505243088655862
    },
    {
      "year": "2013",
      "revenue": 6142,
      "operating_profit": 412,
      "net_income": 324,
      "op_margin": 6.707912732009118
    },
    {
      "year": "2012",
      "revenue": 4950,
      "operating_profit": 252,
      "net_income": 195,
      "op_margin": 5.090909090909091
    },
    {
      "year": "2011",
      "revenue": 3449,
      "operating_profit": 232,
      "net_income": 219,
      "op_margin": 6.726587416642506
    },
    {
      "year": "2010",
      "revenue": 2491,
      "operating_profit": 171,
      "net_income": 105,
      "op_margin": 6.864712966680048
    },
    {
      "year": "2009",
      "revenue": 1330,
      "operating_profit": 69,
      "net_income": 71,
      "op_margin": 5.18796992481203
    },
    {
      "year": "2008",
      "revenue": 750,
      "operating_profit": -26,
      "net_income": -19,
      "op_margin": -3.4666666666666663
    },
    {
      "year": "2007",
      "revenue": 123,
      "operating_profit": 34,
      "net_income": 27,
      "op_margin": 27.64227642276423
    },
    {
      "year": "2006",
      "revenue": 201,
      "operating_profit": 29,
      "net_income": 23,
      "op_margin": 14.427860696517413
    },
    {
      "year": "2005",
      "revenue": 129,
      "operating_profit": 16,
      "net_income": 15,
      "op_margin": 12.4031007751938
    },
    {
      "year": "2004",
      "revenue": 116,
      "operating_profit": 16,
      "net_income": 13,
      "op_margin": 13.793103448275861
    }
  ],
  "ratios": {
    "roe": -6.12,
    "eps": -138,
    "bps": 2202,
    "debt_ratio": 47.36
  }
}
