{
  "ticker": "063160",
  "name": "종근당바이오",
  "market": "KOSPI",
  "sector": "Healthcare",
  "quarterly": [
    {
      "period": "2024Q4",
      "stac_yymm": "202412",
      "revenue": 1718,
      "operating_profit": 92,
      "net_income": 87,
      "op_margin": 5.355064027939465,
      "yoy_revenue": 385.31073446327684,
      "yoy_op": 229.5774647887324,
      "qoq_revenue": 385.31073446327684,
      "qoq_op": 229.5774647887324
    },
    {
      "period": "2023Q4",
      "stac_yymm": "202312",
      "revenue": 354,
      "operating_profit": -71,
      "net_income": -81,
      "op_margin": -20.056497175141246,
      "yoy_revenue": 1.4326647564469914,
      "yoy_op": 26.804123711340207,
      "qoq_revenue": -16.312056737588655,
      "qoq_op": -2.898550724637681
    },
    {
      "period": "2023Q3",
      "stac_yymm": "202309",
      "revenue": 423,
      "operating_profit": -69,
      "net_income": -64,
      "op_margin": -16.312056737588655,
      "yoy_revenue": 12.5,
      "yoy_op": -146.42857142857142,
      "qoq_revenue": 8.461538461538462,
      "qoq_op": -1.4705882352941175
    },
    {
      "period": "2023Q2",
      "stac_yymm": "202306",
      "revenue": 390,
      "operating_profit": -68,
      "net_income": -68,
      "op_margin": -17.435897435897434,
      "yoy_revenue": 6.557377049180328,
      "yoy_op": -36,
      "qoq_revenue": -10.755148741418765,
      "qoq_op": -100
    },
    {
      "period": "2023Q1",
      "stac_yymm": "202303",
      "revenue": 437,
      "operating_profit": -34,
      "net_income": -29,
      "op_margin": -7.780320366132723,
      "yoy_revenue": -6.823027718550106,
      "yoy_op": -209.0909090909091,
      "qoq_revenue": 25.214899713467048,
      "qoq_op": 64.94845360824742
    },
    {
      "period": "2022Q4",
      "stac_yymm": "202212",
      "revenue": 349,
      "operating_profit": -97,
      "net_income": -71,
      "op_margin": -27.793696275071632,
      "yoy_revenue": 5.120481927710843,
      "yoy_op": -120.45454545454545,
      "qoq_revenue": -7.180851063829788,
      "qoq_op": -246.42857142857144
    },
    {
      "period": "2022Q3",
      "stac_yymm": "202209",
      "revenue": 376,
      "operating_profit": -28,
      "net_income": -35,
      "op_margin": -7.446808510638298,
      "yoy_revenue": -1.0526315789473684,
      "yoy_op": 37.77777777777778,
      "qoq_revenue": 2.73224043715847,
      "qoq_op": 44
    },
    {
      "period": "2022Q2",
      "stac_yymm": "202206",
      "revenue": 366,
      "operating_profit": -50,
      "net_income": -49,
      "op_margin": -13.661202185792352,
      "yoy_revenue": -2.4,
      "yoy_op": -194.11764705882354,
      "qoq_revenue": -21.961620469083158,
      "qoq_op": -354.54545454545456
    },
    {
      "period": "2022Q1",
      "stac_yymm": "202203",
      "revenue": 469,
      "operating_profit": -11,
      "net_income": -12,
      "op_margin": -2.345415778251599,
      "yoy_revenue": 40,
      "yoy_op": 60.71428571428571,
      "qoq_revenue": 41.265060240963855,
      "qoq_op": 75
    },
    {
      "period": "2021Q4",
      "stac_yymm": "202112",
      "revenue": 332,
      "operating_profit": -44,
      "net_income": -9,
      "op_margin": -13.253012048192772,
      "yoy_revenue": 23.88059701492537,
      "yoy_op": -388.88888888888886,
      "qoq_revenue": -12.631578947368421,
      "qoq_op": 2.2222222222222223
    },
    {
      "period": "2021Q3",
      "stac_yymm": "202109",
      "revenue": 380,
      "operating_profit": -45,
      "net_income": -42,
      "op_margin": -11.842105263157894,
      "yoy_revenue": 16.207951070336392,
      "yoy_op": -475,
      "qoq_revenue": 1.3333333333333335,
      "qoq_op": -164.70588235294116
    },
    {
      "period": "2021Q2",
      "stac_yymm": "202106",
      "revenue": 375,
      "operating_profit": -17,
      "net_income": 5,
      "op_margin": -4.533333333333333,
      "yoy_revenue": 8.069164265129682,
      "yoy_op": -147.22222222222223,
      "qoq_revenue": 11.940298507462686,
      "qoq_op": 39.285714285714285
    },
    {
      "period": "2021Q1",
      "stac_yymm": "202103",
      "revenue": 335,
      "operating_profit": -28,
      "net_income": -20,
      "op_margin": -8.358208955223882,
      "yoy_revenue": 10.197368421052632,
      "yoy_op": -187.5,
      "qoq_revenue": 25,
      "qoq_op": -211.11111111111111
    },
    {
      "period": "2020Q4",
      "stac_yymm": "202012",
      "revenue": 268,
      "operating_profit": -9,
      "net_income": -10,
      "op_margin": -3.3582089552238807,
      "yoy_revenue": -29.47368421052631,
      "yoy_op": -120.45454545454545,
      "qoq_revenue": -18.04281345565749,
      "qoq_op": -175
    },
    {
      "period": "2020Q3",
      "stac_yymm": "202009",
      "revenue": 327,
      "operating_profit": 12,
      "net_income": 14,
      "op_margin": 3.669724770642202,
      "yoy_revenue": -6.303724928366762,
      "yoy_op": -72.09302325581395,
      "qoq_revenue": -5.763688760806916,
      "qoq_op": -66.66666666666666
    },
    {
      "period": "2020Q2",
      "stac_yymm": "202006",
      "revenue": 347,
      "operating_profit": 36,
      "net_income": 33,
      "op_margin": 10.37463976945245,
      "yoy_revenue": 5.151515151515151,
      "yoy_op": -14.285714285714285,
      "qoq_revenue": 14.144736842105262,
      "qoq_op": 12.5
    },
    {
      "period": "2020Q1",
      "stac_yymm": "202003",
      "revenue": 304,
      "operating_profit": 32,
      "net_income": 25,
      "op_margin": 10.526315789473683,
      "yoy_revenue": -2.8753993610223643,
      "yoy_op": 18.51851851851852,
      "qoq_revenue": -20,
      "qoq_op": -27.27272727272727
    },
    {
      "period": "2019Q4",
      "stac_yymm": "201912",
      "revenue": 380,
      "operating_profit": 44,
      "net_income": 35,
      "op_margin": 11.578947368421053,
      "yoy_revenue": 25.412541254125415,
      "yoy_op": 131.57894736842107,
      "qoq_revenue": 8.882521489971348,
      "qoq_op": 2.3255813953488373
    },
    {
      "period": "2019Q3",
      "stac_yymm": "201909",
      "revenue": 349,
      "operating_profit": 43,
      "net_income": 33,
      "op_margin": 12.320916905444127,
      "yoy_revenue": 7.384615384615385,
      "yoy_op": 43.333333333333336,
      "qoq_revenue": 5.757575757575758,
      "qoq_op": 2.380952380952381
    },
    {
      "period": "2019Q2",
      "stac_yymm": "201906",
      "revenue": 330,
      "operating_profit": 42,
      "net_income": 32,
      "op_margin": 12.727272727272727,
      "yoy_revenue": -46.51539708265802,
      "yoy_op": -4.545454545454546,
      "qoq_revenue": 5.431309904153355,
      "qoq_op": 55.55555555555556
    },
    {
      "period": "2019Q1",
      "stac_yymm": "201903",
      "revenue": 313,
      "operating_profit": 27,
      "net_income": 23,
      "op_margin": 8.626198083067091,
      "yoy_revenue": null,
      "yoy_op": null,
      "qoq_revenue": 3.3003300330033,
      "qoq_op": 42.10526315789473
    },
    {
      "period": "2018Q4",
      "stac_yymm": "201812",
      "revenue": 303,
      "operating_profit": 19,
      "net_income": 18,
      "op_margin": 6.270627062706271,
      "yoy_revenue": -74.36548223350253,
      "yoy_op": -80.20833333333334,
      "qoq_revenue": -6.769230769230769,
      "qoq_op": -36.666666666666664
    },
    {
      "period": "2018Q3",
      "stac_yymm": "201809",
      "revenue": 325,
      "operating_profit": 30,
      "net_income": 24,
      "op_margin": 9.230769230769232,
      "yoy_revenue": null,
      "yoy_op": null,
      "qoq_revenue": -47.3257698541329,
      "qoq_op": -31.818181818181817
    },
    {
      "period": "2018Q2",
      "stac_yymm": "201806",
      "revenue": 617,
      "operating_profit": 44,
      "net_income": 38,
      "op_margin": 7.13128038897893,
      "yoy_revenue": null,
      "yoy_op": null,
      "qoq_revenue": -47.800338409475465,
      "qoq_op": -54.166666666666664
    },
    {
      "period": "2017Q4",
      "stac_yymm": "201712",
      "revenue": 1182,
      "operating_profit": 96,
      "net_income": 80,
      "op_margin": 8.121827411167512,
      "yoy_revenue": 4.601769911504425,
      "yoy_op": -20.66115702479339,
      "qoq_revenue": 4.601769911504425,
      "qoq_op": -20.66115702479339
    },
    {
      "period": "2016Q4",
      "stac_yymm": "201612",
      "revenue": 1130,
      "operating_profit": 121,
      "net_income": 94,
      "op_margin": 10.707964601769913,
      "yoy_revenue": 5.904404873477039,
      "yoy_op": 49.382716049382715,
      "qoq_revenue": 5.904404873477039,
      "qoq_op": 49.382716049382715
    },
    {
      "period": "2015Q4",
      "stac_yymm": "201512",
      "revenue": 1067,
      "operating_profit": 81,
      "net_income": 67,
      "op_margin": 7.591377694470477,
      "yoy_revenue": 0.28195488721804507,
      "yoy_op": 526.3157894736843,
      "qoq_revenue": 0.28195488721804507,
      "qoq_op": 526.3157894736843
    },
    {
      "period": "2014Q4",
      "stac_yymm": "201412",
      "revenue": 1064,
      "operating_profit": -19,
      "net_income": -11,
      "op_margin": -1.7857142857142856,
      "yoy_revenue": 5.9760956175298805,
      "yoy_op": -200,
      "qoq_revenue": 5.9760956175298805,
      "qoq_op": -200
    },
    {
      "period": "2013Q4",
      "stac_yymm": "201312",
      "revenue": 1004,
      "operating_profit": 19,
      "net_income": 17,
      "op_margin": 1.8924302788844622,
      "yoy_revenue": -11.775043936731107,
      "yoy_op": -76.5432098765432,
      "qoq_revenue": -11.775043936731107,
      "qoq_op": -76.5432098765432
    },
    {
      "period": "2012Q4",
      "stac_yymm": "201212",
      "revenue": 1138,
      "operating_profit": 81,
      "net_income": 71,
      "op_margin": 7.117750439367311,
      "yoy_revenue": null,
      "yoy_op": null,
      "qoq_revenue": null,
      "qoq_op": null
    }
  ],
  "annual": [
    {
      "year": "2024",
      "revenue": 1718,
      "operating_profit": 92,
      "net_income": 87,
      "op_margin": 5.355064027939465
    },
    {
      "year": "2023",
      "revenue": 1604,
      "operating_profit": -242,
      "net_income": -242,
      "op_margin": -15.087281795511224
    },
    {
      "year": "2022",
      "revenue": 1560,
      "operating_profit": -186,
      "net_income": -167,
      "op_margin": -11.923076923076923
    },
    {
      "year": "2021",
      "revenue": 1422,
      "operating_profit": -134,
      "net_income": -66,
      "op_margin": -9.423347398030943
    },
    {
      "year": "2020",
      "revenue": 1246,
      "operating_profit": 71,
      "net_income": 62,
      "op_margin": 5.698234349919743
    },
    {
      "year": "2019",
      "revenue": 1372,
      "operating_profit": 156,
      "net_income": 123,
      "op_margin": 11.370262390670554
    },
    {
      "year": "2018",
      "revenue": 1245,
      "operating_profit": 93,
      "net_income": 80,
      "op_margin": 7.46987951807229
    },
    {
      "year": "2017",
      "revenue": 1182,
      "operating_profit": 96,
      "net_income": 80,
      "op_margin": 8.121827411167512
    },
    {
      "year": "2016",
      "revenue": 1130,
      "operating_profit": 121,
      "net_income": 94,
      "op_margin": 10.707964601769913
    },
    {
      "year": "2015",
      "revenue": 1067,
      "operating_profit": 81,
      "net_income": 67,
      "op_margin": 7.591377694470477
    },
    {
      "year": "2014",
      "revenue": 1064,
      "operating_profit": -19,
      "net_income": -11,
      "op_margin": -1.7857142857142856
    },
    {
      "year": "2013",
      "revenue": 1004,
      "operating_profit": 19,
      "net_income": 17,
      "op_margin": 1.8924302788844622
    },
    {
      "year": "2012",
      "revenue": 1138,
      "operating_profit": 81,
      "net_income": 71,
      "op_margin": 7.117750439367311
    },
    {
      "year": "2011",
      "revenue": 1105,
      "operating_profit": 130,
      "net_income": 109,
      "op_margin": 11.76470588235294
    },
    {
      "year": "2010",
      "revenue": 1216,
      "operating_profit": 185,
      "net_income": 165,
      "op_margin": 15.213815789473683
    },
    {
      "year": "2009",
      "revenue": 1066,
      "operating_profit": 168,
      "net_income": 162,
      "op_margin": 15.75984990619137
    },
    {
      "year": "2008",
      "revenue": 834,
      "operating_profit": 99,
      "net_income": 87,
      "op_margin": 11.870503597122301
    },
    {
      "year": "2007",
      "revenue": 664,
      "operating_profit": -45,
      "net_income": -33,
      "op_margin": -6.77710843373494
    },
    {
      "year": "2006",
      "revenue": 722,
      "operating_profit": 0,
      "net_income": 4,
      "op_margin": 0
    },
    {
      "year": "2005",
      "revenue": 644,
      "operating_profit": -138,
      "net_income": -134,
      "op_margin": -21.428571428571427
    },
    {
      "year": "2004",
      "revenue": 687,
      "operating_profit": 10,
      "net_income": 11,
      "op_margin": 1.455604075691412
    }
  ],
  "ratios": {
    "roe": 6.85,
    "eps": 1586,
    "bps": 23881,
    "debt_ratio": 117.15
  }
}
