{
  "ticker": "187420",
  "name": "HLB제넥스",
  "quarterly": [
    {
      "period": "2018QQ3",
      "stac_yymm": "201809",
      "revenue": 92,
      "operating_profit": 0,
      "net_income": -2,
      "op_margin": 0
    },
    {
      "period": "2018QQ4",
      "stac_yymm": "201812",
      "revenue": 115,
      "operating_profit": 0,
      "net_income": -24,
      "op_margin": 0
    },
    {
      "period": "2019QQ1",
      "stac_yymm": "201903",
      "revenue": 37,
      "operating_profit": 0,
      "net_income": 1,
      "op_margin": 0
    },
    {
      "period": "2019QQ2",
      "stac_yymm": "201906",
      "revenue": 75,
      "operating_profit": 0,
      "net_income": -8,
      "op_margin": 0
    },
    {
      "period": "2019QQ3",
      "stac_yymm": "201909",
      "revenue": 105,
      "operating_profit": 0,
      "net_income": -36,
      "op_margin": 0,
      "yoy_revenue": 14.130434782608695
    },
    {
      "period": "2019QQ4",
      "stac_yymm": "201912",
      "revenue": 149,
      "operating_profit": 0,
      "net_income": -55,
      "op_margin": 0,
      "yoy_revenue": 29.565217391304348
    },
    {
      "period": "2020QQ1",
      "stac_yymm": "202003",
      "revenue": 50,
      "operating_profit": 0,
      "net_income": 0,
      "op_margin": 0,
      "yoy_revenue": 35.13513513513514
    },
    {
      "period": "2020QQ2",
      "stac_yymm": "202006",
      "revenue": 103,
      "operating_profit": 0,
      "net_income": -7,
      "op_margin": 0,
      "yoy_revenue": 37.333333333333336
    },
    {
      "period": "2020QQ3",
      "stac_yymm": "202009",
      "revenue": 144,
      "operating_profit": 0,
      "net_income": -30,
      "op_margin": 0,
      "yoy_revenue": 37.142857142857146
    },
    {
      "period": "2020QQ4",
      "stac_yymm": "202012",
      "revenue": 188,
      "operating_profit": 0,
      "net_income": -121,
      "op_margin": 0,
      "yoy_revenue": 26.174496644295303
    },
    {
      "period": "2021QQ1",
      "stac_yymm": "202103",
      "revenue": 55,
      "operating_profit": 0,
      "net_income": -8,
      "op_margin": 0,
      "yoy_revenue": 10
    },
    {
      "period": "2021QQ2",
      "stac_yymm": "202106",
      "revenue": 121,
      "operating_profit": 0,
      "net_income": 23,
      "op_margin": 0,
      "yoy_revenue": 17.475728155339805
    },
    {
      "period": "2021QQ3",
      "stac_yymm": "202109",
      "revenue": 186,
      "operating_profit": 0,
      "net_income": 3,
      "op_margin": 0,
      "yoy_revenue": 29.166666666666668
    },
    {
      "period": "2021QQ4",
      "stac_yymm": "202112",
      "revenue": 259,
      "operating_profit": 0,
      "net_income": -85,
      "op_margin": 0,
      "yoy_revenue": 37.765957446808514
    },
    {
      "period": "2022QQ1",
      "stac_yymm": "202203",
      "revenue": 60,
      "operating_profit": 0,
      "net_income": -22,
      "op_margin": 0,
      "yoy_revenue": 9.090909090909092
    },
    {
      "period": "2022QQ2",
      "stac_yymm": "202206",
      "revenue": 134,
      "operating_profit": 0,
      "net_income": -1,
      "op_margin": 0,
      "yoy_revenue": 10.743801652892563
    },
    {
      "period": "2022QQ3",
      "stac_yymm": "202209",
      "revenue": 200,
      "operating_profit": 0,
      "net_income": -25,
      "op_margin": 0,
      "yoy_revenue": 7.526881720430108
    },
    {
      "period": "2022QQ4",
      "stac_yymm": "202212",
      "revenue": 278,
      "operating_profit": 0,
      "net_income": -134,
      "op_margin": 0,
      "yoy_revenue": 7.335907335907336
    },
    {
      "period": "2023QQ1",
      "stac_yymm": "202303",
      "revenue": 61,
      "operating_profit": 0,
      "net_income": -33,
      "op_margin": 0,
      "yoy_revenue": 1.6666666666666667
    },
    {
      "period": "2023QQ2",
      "stac_yymm": "202306",
      "revenue": 110,
      "operating_profit": 0,
      "net_income": -12,
      "op_margin": 0,
      "yoy_revenue": -17.91044776119403
    },
    {
      "period": "2023QQ3",
      "stac_yymm": "202309",
      "revenue": 175,
      "operating_profit": 0,
      "net_income": -58,
      "op_margin": 0,
      "yoy_revenue": -12.5
    },
    {
      "period": "2023QQ4",
      "stac_yymm": "202312",
      "revenue": 270,
      "operating_profit": 0,
      "net_income": -7,
      "op_margin": 0,
      "yoy_revenue": -2.877697841726619
    },
    {
      "period": "2024QQ1",
      "stac_yymm": "202403",
      "revenue": 71,
      "operating_profit": 0,
      "net_income": -14,
      "op_margin": 0,
      "yoy_revenue": 16.39344262295082
    },
    {
      "period": "2024QQ2",
      "stac_yymm": "202406",
      "revenue": 162,
      "operating_profit": 0,
      "net_income": -10,
      "op_margin": 0,
      "yoy_revenue": 47.27272727272727
    },
    {
      "period": "2024QQ3",
      "stac_yymm": "202409",
      "revenue": 254,
      "operating_profit": 0,
      "net_income": -15,
      "op_margin": 0,
      "yoy_revenue": 45.14285714285714
    },
    {
      "period": "2024QQ4",
      "stac_yymm": "202412",
      "revenue": 354,
      "operating_profit": 0,
      "net_income": -179,
      "op_margin": 0,
      "yoy_revenue": 31.11111111111111
    },
    {
      "period": "2025QQ1",
      "stac_yymm": "202503",
      "revenue": 107,
      "operating_profit": 0,
      "net_income": -12,
      "op_margin": 0,
      "yoy_revenue": 50.70422535211267
    },
    {
      "period": "2025QQ2",
      "stac_yymm": "202506",
      "revenue": 207,
      "operating_profit": 0,
      "net_income": 179,
      "op_margin": 0,
      "yoy_revenue": 27.77777777777778
    },
    {
      "period": "2025QQ3",
      "stac_yymm": "202509",
      "revenue": 309,
      "operating_profit": 0,
      "net_income": 139,
      "op_margin": 0,
      "yoy_revenue": 21.653543307086615
    },
    {
      "period": "2025QQ4",
      "stac_yymm": "202512",
      "revenue": 434,
      "operating_profit": 0,
      "net_income": 229,
      "op_margin": 0,
      "yoy_revenue": 22.598870056497177
    }
  ],
  "annual": [],
  "ratios": {
    "per": 0,
    "pbr": 0,
    "roe": 69.88,
    "eps": 775,
    "bps": 1403,
    "debt_ratio": 148.1
  }
}
